Workbook

Sheet Torque Plan Summary · Scenario
A1: Torque Plan Summary · Scenario comparison: month 12 (Sep 2027)
A2: Financial model (4 pages) · Main Scenario
A4: Variable / dimension | B4: 2027-09 | C4: 2027-09 > Conservative | D4: 2027-09 > Optimistic
A5: Paying customers | B5: =SUM('Monthly Financial Plan · Torque'!M7,'Monthly Financial Plan · Torque'!M8,'Monthly Financial Plan · Torque'!M9) -> 135.7862 | C5: =SUM('Model inputs'!P85,'Model inputs'!P86,'Model inputs'!P87) -> 31.047134 | D5: =SUM('Model inputs'!P81,'Model inputs'!P82,'Model inputs'!P83) -> 375.68726
A6: Verified pull requests | B6: =SUM('Monthly Financial Plan · Torque'!M15,'Monthly Financial Plan · Torque'!M16,'Monthly Financial Plan · Torque'!M17)*'Torque Assumptions · Run cost a'!B17 -> 3964.3736 | C6: =SUM('Model inputs'!P34,'Model inputs'!P35,'Model inputs'!P36)*'Model inputs'!B125 -> 868.67197 | D6: =SUM('Model inputs'!P30,'Model inputs'!P31,'Model inputs'!P32)*'Model inputs'!B124 -> 10720.107
A7: Total revenue | B7: =SUM('Monthly Financial Plan · Torque'!M20,'Monthly Financial Plan · Torque'!M21,'Monthly Financial Plan · Torque'!M22)+SUM('Monthly Financial Plan · Torque'!M24,'Monthly Financial Plan · Torque'!M25,'Monthly Financial Plan · Torque'!M26) -> 16691.007 | C7: =SUM('Model inputs'!P109,'Model inputs'!P110,'Model inputs'!P111)+SUM('Model inputs'!P73,'Model inputs'!P74,'Model inputs'!P75) -> 3955.5457 | D7: =SUM('Model inputs'!P105,'Model inputs'!P106,'Model inputs'!P107)+SUM('Model inputs'!P69,'Model inputs'!P70,'Model inputs'!P71) -> 45459.549
A8: Cost of revenue | B8: ='Monthly Financial Plan · Torque'!M28+'Monthly Financial Plan · Torque'!M29+'Monthly Financial Plan · Torque'!M30+'Monthly Financial Plan · Torque'!M31+'Monthly Financial Plan · Torque'!M32+'Monthly Financial Plan · Torque'!M33 -> 7797.433 | C8: ='Model inputs'!P39+'Model inputs'!P93+'Model inputs'!P62+'Model inputs'!P99+'Model inputs'!P24+'Model inputs'!P90 -> 3009.3765 | D8: ='Model inputs'!P38+'Model inputs'!P92+'Model inputs'!P61+'Model inputs'!P98+'Model inputs'!P23+'Model inputs'!P89 -> 15195.568
A9: Gross margin before credits | B9: =IFERROR('Monthly Financial Plan · Torque'!M35/'Torque Plan Summary · Scenario'!B7,"") -> 0.53283628 | C9: =IFERROR('Model inputs'!P19/'Torque Plan Summary · Scenario'!C7,"") -> 0.23920068 | D9: =IFERROR('Model inputs'!P18/'Torque Plan Summary · Scenario'!D7,"") -> 0.66573429
A10: Operating expenses | B10: ='Monthly Financial Plan · Torque'!M41+'Monthly Financial Plan · Torque'!M42+'Monthly Financial Plan · Torque'!M43 -> 700 | C10: ='Model inputs'!P118+'Model inputs'!P96+'Model inputs'!P42 -> 700 | D10: ='Model inputs'!P117+'Model inputs'!P95+'Model inputs'!P41 -> 700
A11: Net cash flow before credits | B11: ='Monthly Financial Plan · Torque'!M35-'Torque Plan Summary · Scenario'!B10 -> 8193.5743 | C11: ='Model inputs'!P19-'Torque Plan Summary · Scenario'!C10 -> 246.16924 | D11: ='Model inputs'!P18-'Torque Plan Summary · Scenario'!D10 -> 29563.98
A12: AI spend limit at target margin | B12: ='Torque Plan Summary · Scenario'!B7*(1-'Torque Assumptions · Growth & o'!B12)-'Monthly Financial Plan · Torque'!M32-'Monthly Financial Plan · Torque'!M33-'Monthly Financial Plan · Torque'!M30-'Monthly Financial Plan · Torque'!M31 -> 5001.8953 | C12: ='Torque Plan Summary · Scenario'!C7*(1-'Model inputs'!B115)-'Model inputs'!P24-'Model inputs'!P90-'Model inputs'!P62-'Model inputs'!P99 -> 1062.1565 | D12: ='Torque Plan Summary · Scenario'!D7*(1-'Model inputs'!B114)-'Model inputs'!P23-'Model inputs'!P89-'Model inputs'!P61-'Model inputs'!P98 -> 13946.948

Sheet Monthly Financial Plan · Torque
A1: Monthly Financial Plan · Torque monthly financial plan
A2: Financial model (4 pages) · Main Scenario
A4: Variable / dimension | B4: 2026-10 | C4: 2026-11 | D4: 2026-12 | E4: 2027-01 | F4: 2027-02 | G4: 2027-03 | H4: 2027-04 | I4: 2027-05 | J4: 2027-06 | K4: 2027-07 | L4: 2027-08 | M4: 2027-09
A5: New customers | B5: ='Torque Assumptions · Growth & o'!B5*IF(AND((1+'Torque Assumptions · Growth & o'!B6)=0,DATEDIF(DATE(2026,10,1),DATE(2026,10,1),"M")=0),SQRT(-1),(1+'Torque Assumptions · Growth & o'!B6)^DATEDIF(DATE(2026,10,1),DATE(2026,10,1),"M")) -> 3 | C5: ='Torque Assumptions · Growth & o'!B5*IF(AND((1+'Torque Assumptions · Growth & o'!B6)=0,DATEDIF(DATE(2026,10,1),DATE(2026,11,1),"M")=0),SQRT(-1),(1+'Torque Assumptions · Growth & o'!B6)^DATEDIF(DATE(2026,10,1),DATE(2026,11,1),"M")) -> 3.75 | D5: ='Torque Assumptions · Growth & o'!B5*IF(AND((1+'Torque Assumptions · Growth & o'!B6)=0,DATEDIF(DATE(2026,10,1),DATE(2026,12,1),"M")=0),SQRT(-1),(1+'Torque Assumptions · Growth & o'!B6)^DATEDIF(DATE(2026,10,1),DATE(2026,12,1),"M")) -> 4.6875 | E5: ='Torque Assumptions · Growth & o'!B5*IF(AND((1+'Torque Assumptions · Growth & o'!B6)=0,DATEDIF(DATE(2026,10,1),DATE(2027,1,1),"M")=0),SQRT(-1),(1+'Torque Assumptions · Growth & o'!B6)^DATEDIF(DATE(2026,10,1),DATE(2027,1,1),"M")) -> 5.859375 | F5: ='Torque Assumptions · Growth & o'!B5*IF(AND((1+'Torque Assumptions · Growth & o'!B6)=0,DATEDIF(DATE(2026,10,1),DATE(2027,2,1),"M")=0),SQRT(-1),(1+'Torque Assumptions · Growth & o'!B6)^DATEDIF(DATE(2026,10,1),DATE(2027,2,1),"M")) -> 7.3242188 | G5: ='Torque Assumptions · Growth & o'!B5*IF(AND((1+'Torque Assumptions · Growth & o'!B6)=0,DATEDIF(DATE(2026,10,1),DATE(2027,3,1),"M")=0),SQRT(-1),(1+'Torque Assumptions · Growth & o'!B6)^DATEDIF(DATE(2026,10,1),DATE(2027,3,1),"M")) -> 9.1552734 | H5: ='Torque Assumptions · Growth & o'!B5*IF(AND((1+'Torque Assumptions · Growth & o'!B6)=0,DATEDIF(DATE(2026,10,1),DATE(2027,4,1),"M")=0),SQRT(-1),(1+'Torque Assumptions · Growth & o'!B6)^DATEDIF(DATE(2026,10,1),DATE(2027,4,1),"M")) -> 11.444092 | I5: ='Torque Assumptions · Growth & o'!B5*IF(AND((1+'Torque Assumptions · Growth & o'!B6)=0,DATEDIF(DATE(2026,10,1),DATE(2027,5,1),"M")=0),SQRT(-1),(1+'Torque Assumptions · Growth & o'!B6)^DATEDIF(DATE(2026,10,1),DATE(2027,5,1),"M")) -> 14.305115 | J5: ='Torque Assumptions · Growth & o'!B5*IF(AND((1+'Torque Assumptions · Growth & o'!B6)=0,DATEDIF(DATE(2026,10,1),DATE(2027,6,1),"M")=0),SQRT(-1),(1+'Torque Assumptions · Growth & o'!B6)^DATEDIF(DATE(2026,10,1),DATE(2027,6,1),"M")) -> 17.881393 | K5: ='Torque Assumptions · Growth & o'!B5*IF(AND((1+'Torque Assumptions · Growth & o'!B6)=0,DATEDIF(DATE(2026,10,1),DATE(2027,7,1),"M")=0),SQRT(-1),(1+'Torque Assumptions · Growth & o'!B6)^DATEDIF(DATE(2026,10,1),DATE(2027,7,1),"M")) -> 22.351742 | L5: ='Torque Assumptions · Growth & o'!B5*IF(AND((1+'Torque Assumptions · Growth & o'!B6)=0,DATEDIF(DATE(2026,10,1),DATE(2027,8,1),"M")=0),SQRT(-1),(1+'Torque Assumptions · Growth & o'!B6)^DATEDIF(DATE(2026,10,1),DATE(2027,8,1),"M")) -> 27.939677 | M5: ='Torque Assumptions · Growth & o'!B5*IF(AND((1+'Torque Assumptions · Growth & o'!B6)=0,DATEDIF(DATE(2026,10,1),DATE(2027,9,1),"M")=0),SQRT(-1),(1+'Torque Assumptions · Growth & o'!B6)^DATEDIF(DATE(2026,10,1),DATE(2027,9,1),"M")) -> 34.924597
A6: Paying customers | B6: =SUM('Monthly Financial Plan · Torque'!B7,'Monthly Financial Plan · Torque'!B8,'Monthly Financial Plan · Torque'!B9) -> 3 | C6: =SUM('Monthly Financial Plan · Torque'!C7,'Monthly Financial Plan · Torque'!C8,'Monthly Financial Plan · Torque'!C9) -> 6.564 | D6: =SUM('Monthly Financial Plan · Torque'!D7,'Monthly Financial Plan · Torque'!D8,'Monthly Financial Plan · Torque'!D9) -> 10.84563 | E6: =SUM('Monthly Financial Plan · Torque'!E7,'Monthly Financial Plan · Torque'!E8,'Monthly Financial Plan · Torque'!E9) -> 16.036016 | F6: =SUM('Monthly Financial Plan · Torque'!F7,'Monthly Financial Plan · Torque'!F8,'Monthly Financial Plan · Torque'!F9) -> 22.373223 | G6: =SUM('Monthly Financial Plan · Torque'!G7,'Monthly Financial Plan · Torque'!G8,'Monthly Financial Plan · Torque'!G9) -> 30.154051 | H6: =SUM('Monthly Financial Plan · Torque'!H7,'Monthly Financial Plan · Torque'!H8,'Monthly Financial Plan · Torque'!H9) -> 39.74878 | I6: =SUM('Monthly Financial Plan · Torque'!I7,'Monthly Financial Plan · Torque'!I8,'Monthly Financial Plan · Torque'!I9) -> 51.619592 | ... M6: =SUM('Monthly Financial Plan · Torque'!M7,'Monthly Financial Plan · Torque'!M8,'Monthly Financial Plan · Torque'!M9) -> 135.7862
A7: Maintainer | B7: ='Model inputs'!D77*(1-'Torque Assumptions · Tier prici'!H5)+'Monthly Financial Plan · Torque'!B5*'Torque Assumptions · Tier prici'!G5 -> 1.5 | C7: ='Monthly Financial Plan · Torque'!B7*(1-'Torque Assumptions · Tier prici'!H5)+'Monthly Financial Plan · Torque'!C5*'Torque Assumptions · Tier prici'!G5 -> 3.255 | D7: ='Monthly Financial Plan · Torque'!C7*(1-'Torque Assumptions · Tier prici'!H5)+'Monthly Financial Plan · Torque'!D5*'Torque Assumptions · Tier prici'!G5 -> 5.33835 | E7: ='Monthly Financial Plan · Torque'!D7*(1-'Torque Assumptions · Tier prici'!H5)+'Monthly Financial Plan · Torque'!E5*'Torque Assumptions · Tier prici'!G5 -> 7.8409695 | F7: ='Monthly Financial Plan · Torque'!E7*(1-'Torque Assumptions · Tier prici'!H5)+'Monthly Financial Plan · Torque'!F5*'Torque Assumptions · Tier prici'!G5 -> 10.875801 | G7: ='Monthly Financial Plan · Torque'!F7*(1-'Torque Assumptions · Tier prici'!H5)+'Monthly Financial Plan · Torque'!G5*'Torque Assumptions · Tier prici'!G5 -> 14.583374 | H7: ='Monthly Financial Plan · Torque'!G7*(1-'Torque Assumptions · Tier prici'!H5)+'Monthly Financial Plan · Torque'!H5*'Torque Assumptions · Tier prici'!G5 -> 19.13875 | I7: ='Monthly Financial Plan · Torque'!H7*(1-'Torque Assumptions · Tier prici'!H5)+'Monthly Financial Plan · Torque'!I5*'Torque Assumptions · Tier prici'!G5 -> 24.760207 | J7: ='Monthly Financial Plan · Torque'!I7*(1-'Torque Assumptions · Tier prici'!H5)+'Monthly Financial Plan · Torque'!J5*'Torque Assumptions · Tier prici'!G5 -> 31.720087 | K7: ='Monthly Financial Plan · Torque'!J7*(1-'Torque Assumptions · Tier prici'!H5)+'Monthly Financial Plan · Torque'!K5*'Torque Assumptions · Tier prici'!G5 -> 40.358351 | L7: ='Monthly Financial Plan · Torque'!K7*(1-'Torque Assumptions · Tier prici'!H5)+'Monthly Financial Plan · Torque'!L5*'Torque Assumptions · Tier prici'!G5 -> 51.099522 | M7: ='Monthly Financial Plan · Torque'!L7*(1-'Torque Assumptions · Tier prici'!H5)+'Monthly Financial Plan · Torque'!M5*'Torque Assumptions · Tier prici'!G5 -> 64.473858
A8: Starter | B8: ='Model inputs'!D78*(1-'Torque Assumptions · Tier prici'!H6)+'Monthly Financial Plan · Torque'!B5*'Torque Assumptions · Tier prici'!G6 -> 1.05 | C8: ='Monthly Financial Plan · Torque'!B8*(1-'Torque Assumptions · Tier prici'!H6)+'Monthly Financial Plan · Torque'!C5*'Torque Assumptions · Tier prici'!G6 -> 2.31 | D8: ='Monthly Financial Plan · Torque'!C8*(1-'Torque Assumptions · Tier prici'!H6)+'Monthly Financial Plan · Torque'!D5*'Torque Assumptions · Tier prici'!G6 -> 3.835125 | E8: ='Monthly Financial Plan · Torque'!D8*(1-'Torque Assumptions · Tier prici'!H6)+'Monthly Financial Plan · Torque'!E5*'Torque Assumptions · Tier prici'!G6 -> 5.69415 | F8: ='Monthly Financial Plan · Torque'!E8*(1-'Torque Assumptions · Tier prici'!H6)+'Monthly Financial Plan · Torque'!F5*'Torque Assumptions · Tier prici'!G6 -> 7.9729191 | G8: ='Monthly Financial Plan · Torque'!F8*(1-'Torque Assumptions · Tier prici'!H6)+'Monthly Financial Plan · Torque'!G5*'Torque Assumptions · Tier prici'!G6 -> 10.778619 | H8: ='Monthly Financial Plan · Torque'!G8*(1-'Torque Assumptions · Tier prici'!H6)+'Monthly Financial Plan · Torque'!H5*'Torque Assumptions · Tier prici'!G6 -> 14.24512 | I8: ='Monthly Financial Plan · Torque'!H8*(1-'Torque Assumptions · Tier prici'!H6)+'Monthly Financial Plan · Torque'!I5*'Torque Assumptions · Tier prici'!G6 -> 18.539654 | J8: ='Monthly Financial Plan · Torque'!I8*(1-'Torque Assumptions · Tier prici'!H6)+'Monthly Financial Plan · Torque'!J5*'Torque Assumptions · Tier prici'!G6 -> 23.871159 | K8: ='Monthly Financial Plan · Torque'!J8*(1-'Torque Assumptions · Tier prici'!H6)+'Monthly Financial Plan · Torque'!K5*'Torque Assumptions · Tier prici'!G6 -> 30.500711 | L8: ='Monthly Financial Plan · Torque'!K8*(1-'Torque Assumptions · Tier prici'!H6)+'Monthly Financial Plan · Torque'!L5*'Torque Assumptions · Tier prici'!G6 -> 38.754562 | M8: ='Monthly Financial Plan · Torque'!L8*(1-'Torque Assumptions · Tier prici'!H6)+'Monthly Financial Plan · Torque'!M5*'Torque Assumptions · Tier prici'!G6 -> 49.040443
A9: Team | B9: ='Model inputs'!D79*(1-'Torque Assumptions · Tier prici'!H7)+'Monthly Financial Plan · Torque'!B5*'Torque Assumptions · Tier prici'!G7 -> 0.45 | C9: ='Monthly Financial Plan · Torque'!B9*(1-'Torque Assumptions · Tier prici'!H7)+'Monthly Financial Plan · Torque'!C5*'Torque Assumptions · Tier prici'!G7 -> 0.999 | D9: ='Monthly Financial Plan · Torque'!C9*(1-'Torque Assumptions · Tier prici'!H7)+'Monthly Financial Plan · Torque'!D5*'Torque Assumptions · Tier prici'!G7 -> 1.672155 | E9: ='Monthly Financial Plan · Torque'!D9*(1-'Torque Assumptions · Tier prici'!H7)+'Monthly Financial Plan · Torque'!E5*'Torque Assumptions · Tier prici'!G7 -> 2.5008966 | F9: ='Monthly Financial Plan · Torque'!E9*(1-'Torque Assumptions · Tier prici'!H7)+'Monthly Financial Plan · Torque'!F5*'Torque Assumptions · Tier prici'!G7 -> 3.5245025 | G9: ='Monthly Financial Plan · Torque'!F9*(1-'Torque Assumptions · Tier prici'!H7)+'Monthly Financial Plan · Torque'!G5*'Torque Assumptions · Tier prici'!G7 -> 4.7920585 | H9: ='Monthly Financial Plan · Torque'!G9*(1-'Torque Assumptions · Tier prici'!H7)+'Monthly Financial Plan · Torque'!H5*'Torque Assumptions · Tier prici'!G7 -> 6.3649105 | I9: ='Monthly Financial Plan · Torque'!H9*(1-'Torque Assumptions · Tier prici'!H7)+'Monthly Financial Plan · Torque'!I5*'Torque Assumptions · Tier prici'!G7 -> 8.3197304 | J9: ='Monthly Financial Plan · Torque'!I9*(1-'Torque Assumptions · Tier prici'!H7)+'Monthly Financial Plan · Torque'!J5*'Torque Assumptions · Tier prici'!G7 -> 10.752347 | K9: ='Monthly Financial Plan · Torque'!J9*(1-'Torque Assumptions · Tier prici'!H7)+'Monthly Financial Plan · Torque'!K5*'Torque Assumptions · Tier prici'!G7 -> 13.782538 | L9: ='Monthly Financial Plan · Torque'!K9*(1-'Torque Assumptions · Tier prici'!H7)+'Monthly Financial Plan · Torque'!L5*'Torque Assumptions · Tier prici'!G7 -> 17.560014 | M9: ='Monthly Financial Plan · Torque'!L9*(1-'Torque Assumptions · Tier prici'!H7)+'Monthly Financial Plan · Torque'!M5*'Torque Assumptions · Tier prici'!G7 -> 22.271903
A10: Churned customers | B10: =SUM('Monthly Financial Plan · Torque'!B11,'Monthly Financial Plan · Torque'!B12,'Monthly Financial Plan · Torque'!B13) -> 0 | C10: =SUM('Monthly Financial Plan · Torque'!C11,'Monthly Financial Plan · Torque'!C12,'Monthly Financial Plan · Torque'!C13) -> 0.186 | D10: =SUM('Monthly Financial Plan · Torque'!D11,'Monthly Financial Plan · Torque'!D12,'Monthly Financial Plan · Torque'!D13) -> 0.40587 | E10: =SUM('Monthly Financial Plan · Torque'!E11,'Monthly Financial Plan · Torque'!E12,'Monthly Financial Plan · Torque'!E13) -> 0.6689889 | F10: =SUM('Monthly Financial Plan · Torque'!F11,'Monthly Financial Plan · Torque'!F12,'Monthly Financial Plan · Torque'!F13) -> 0.98701196 | G10: =SUM('Monthly Financial Plan · Torque'!G11,'Monthly Financial Plan · Torque'!G12,'Monthly Financial Plan · Torque'!G13) -> 1.3744451 | H10: =SUM('Monthly Financial Plan · Torque'!H11,'Monthly Financial Plan · Torque'!H12,'Monthly Financial Plan · Torque'!H13) -> 1.8493626 | I10: =SUM('Monthly Financial Plan · Torque'!I11,'Monthly Financial Plan · Torque'!I12,'Monthly Financial Plan · Torque'!I13) -> 2.4343033 | ... M10: =SUM('Monthly Financial Plan · Torque'!M11,'Monthly Financial Plan · Torque'!M12,'Monthly Financial Plan · Torque'!M13) -> 6.5524903
A11: Maintainer | B11: ='Model inputs'!D77*'Torque Assumptions · Tier prici'!H5 -> 0 | C11: ='Monthly Financial Plan · Torque'!B7*'Torque Assumptions · Tier prici'!H5 -> 0.12 | D11: ='Monthly Financial Plan · Torque'!C7*'Torque Assumptions · Tier prici'!H5 -> 0.2604 | E11: ='Monthly Financial Plan · Torque'!D7*'Torque Assumptions · Tier prici'!H5 -> 0.427068 | F11: ='Monthly Financial Plan · Torque'!E7*'Torque Assumptions · Tier prici'!H5 -> 0.62727756 | G11: ='Monthly Financial Plan · Torque'!F7*'Torque Assumptions · Tier prici'!H5 -> 0.87006411 | H11: ='Monthly Financial Plan · Torque'!G7*'Torque Assumptions · Tier prici'!H5 -> 1.1666699 | I11: ='Monthly Financial Plan · Torque'!H7*'Torque Assumptions · Tier prici'!H5 -> 1.5311 | J11: ='Monthly Financial Plan · Torque'!I7*'Torque Assumptions · Tier prici'!H5 -> 1.9808166 | K11: ='Monthly Financial Plan · Torque'!J7*'Torque Assumptions · Tier prici'!H5 -> 2.537607 | L11: ='Monthly Financial Plan · Torque'!K7*'Torque Assumptions · Tier prici'!H5 -> 3.2286681 | M11: ='Monthly Financial Plan · Torque'!L7*'Torque Assumptions · Tier prici'!H5 -> 4.0879617
A12: Starter | B12: ='Model inputs'!D78*'Torque Assumptions · Tier prici'!H6 -> 0 | C12: ='Monthly Financial Plan · Torque'!B8*'Torque Assumptions · Tier prici'!H6 -> 0.0525 | D12: ='Monthly Financial Plan · Torque'!C8*'Torque Assumptions · Tier prici'!H6 -> 0.1155 | E12: ='Monthly Financial Plan · Torque'!D8*'Torque Assumptions · Tier prici'!H6 -> 0.19175625 | F12: ='Monthly Financial Plan · Torque'!E8*'Torque Assumptions · Tier prici'!H6 -> 0.2847075 | G12: ='Monthly Financial Plan · Torque'!F8*'Torque Assumptions · Tier prici'!H6 -> 0.39864595 | H12: ='Monthly Financial Plan · Torque'!G8*'Torque Assumptions · Tier prici'!H6 -> 0.53893094 | I12: ='Monthly Financial Plan · Torque'!H8*'Torque Assumptions · Tier prici'!H6 -> 0.712256 | J12: ='Monthly Financial Plan · Torque'!I8*'Torque Assumptions · Tier prici'!H6 -> 0.92698271 | K12: ='Monthly Financial Plan · Torque'!J8*'Torque Assumptions · Tier prici'!H6 -> 1.193558 | L12: ='Monthly Financial Plan · Torque'!K8*'Torque Assumptions · Tier prici'!H6 -> 1.5250355 | M12: ='Monthly Financial Plan · Torque'!L8*'Torque Assumptions · Tier prici'!H6 -> 1.9377281
A13: Team | B13: ='Model inputs'!D79*'Torque Assumptions · Tier prici'!H7 -> 0 | C13: ='Monthly Financial Plan · Torque'!B9*'Torque Assumptions · Tier prici'!H7 -> 0.0135 | D13: ='Monthly Financial Plan · Torque'!C9*'Torque Assumptions · Tier prici'!H7 -> 0.02997 | E13: ='Monthly Financial Plan · Torque'!D9*'Torque Assumptions · Tier prici'!H7 -> 0.05016465 | F13: ='Monthly Financial Plan · Torque'!E9*'Torque Assumptions · Tier prici'!H7 -> 0.075026898 | G13: ='Monthly Financial Plan · Torque'!F9*'Torque Assumptions · Tier prici'!H7 -> 0.10573508 | H13: ='Monthly Financial Plan · Torque'!G9*'Torque Assumptions · Tier prici'!H7 -> 0.14376175 | I13: ='Monthly Financial Plan · Torque'!H9*'Torque Assumptions · Tier prici'!H7 -> 0.19094731 | J13: ='Monthly Financial Plan · Torque'!I9*'Torque Assumptions · Tier prici'!H7 -> 0.24959191 | K13: ='Monthly Financial Plan · Torque'!J9*'Torque Assumptions · Tier prici'!H7 -> 0.32257042 | L13: ='Monthly Financial Plan · Torque'!K9*'Torque Assumptions · Tier prici'!H7 -> 0.41347615 | M13: ='Monthly Financial Plan · Torque'!L9*'Torque Assumptions · Tier prici'!H7 -> 0.52680041
A14: Issue runs | B14: =SUM('Monthly Financial Plan · Torque'!B15,'Monthly Financial Plan · Torque'!B16,'Monthly Financial Plan · Torque'!B17) -> 138.075 | C14: =SUM('Monthly Financial Plan · Torque'!C15,'Monthly Financial Plan · Torque'!C16,'Monthly Financial Plan · Torque'!C17) -> 304.845 | D14: =SUM('Monthly Financial Plan · Torque'!D15,'Monthly Financial Plan · Torque'!D16,'Monthly Financial Plan · Torque'!D17) -> 507.76841 | E14: =SUM('Monthly Financial Plan · Torque'!E15,'Monthly Financial Plan · Torque'!E16,'Monthly Financial Plan · Torque'!E17) -> 756.15215 | F14: =SUM('Monthly Financial Plan · Torque'!F15,'Monthly Financial Plan · Torque'!F16,'Monthly Financial Plan · Torque'!F17) -> 1061.6148 | G14: =SUM('Monthly Financial Plan · Torque'!G15,'Monthly Financial Plan · Torque'!G16,'Monthly Financial Plan · Torque'!G17) -> 1438.6653 | H14: =SUM('Monthly Financial Plan · Torque'!H15,'Monthly Financial Plan · Torque'!H16,'Monthly Financial Plan · Torque'!H17) -> 1905.4269 | I14: =SUM('Monthly Financial Plan · Torque'!I15,'Monthly Financial Plan · Torque'!I16,'Monthly Financial Plan · Torque'!I17) -> 2484.541 | ... M14: =SUM('Monthly Financial Plan · Torque'!M15,'Monthly Financial Plan · Torque'!M16,'Monthly Financial Plan · Torque'!M17) -> 6607.2894
A15: Maintainer | B15: ='Monthly Financial Plan · Torque'!B7*'Torque Assumptions · Tier prici'!I5 -> 17.25 | C15: ='Monthly Financial Plan · Torque'!C7*'Torque Assumptions · Tier prici'!I5 -> 37.4325 | D15: ='Monthly Financial Plan · Torque'!D7*'Torque Assumptions · Tier prici'!I5 -> 61.391025 | E15: ='Monthly Financial Plan · Torque'!E7*'Torque Assumptions · Tier prici'!I5 -> 90.171149 | F15: ='Monthly Financial Plan · Torque'!F7*'Torque Assumptions · Tier prici'!I5 -> 125.07172 | G15: ='Monthly Financial Plan · Torque'!G7*'Torque Assumptions · Tier prici'!I5 -> 167.7088 | H15: ='Monthly Financial Plan · Torque'!H7*'Torque Assumptions · Tier prici'!I5 -> 220.09562 | I15: ='Monthly Financial Plan · Torque'!I7*'Torque Assumptions · Tier prici'!I5 -> 284.74238 | J15: ='Monthly Financial Plan · Torque'!J7*'Torque Assumptions · Tier prici'!I5 -> 364.78101 | K15: ='Monthly Financial Plan · Torque'!K7*'Torque Assumptions · Tier prici'!I5 -> 464.12104 | L15: ='Monthly Financial Plan · Torque'!L7*'Torque Assumptions · Tier prici'!I5 -> 587.6445 | M15: ='Monthly Financial Plan · Torque'!M7*'Torque Assumptions · Tier prici'!I5 -> 741.44937
A16: Starter | B16: ='Monthly Financial Plan · Torque'!B8*'Torque Assumptions · Tier prici'!I6 -> 40.95 | C16: ='Monthly Financial Plan · Torque'!C8*'Torque Assumptions · Tier prici'!I6 -> 90.09 | D16: ='Monthly Financial Plan · Torque'!D8*'Torque Assumptions · Tier prici'!I6 -> 149.56987 | E16: ='Monthly Financial Plan · Torque'!E8*'Torque Assumptions · Tier prici'!I6 -> 222.07185 | F16: ='Monthly Financial Plan · Torque'!F8*'Torque Assumptions · Tier prici'!I6 -> 310.94384 | G16: ='Monthly Financial Plan · Torque'!G8*'Torque Assumptions · Tier prici'!I6 -> 420.36613 | H16: ='Monthly Financial Plan · Torque'!H8*'Torque Assumptions · Tier prici'!I6 -> 555.55968 | I16: ='Monthly Financial Plan · Torque'!I8*'Torque Assumptions · Tier prici'!I6 -> 723.04651 | J16: ='Monthly Financial Plan · Torque'!J8*'Torque Assumptions · Tier prici'!I6 -> 930.97521 | K16: ='Monthly Financial Plan · Torque'!K8*'Torque Assumptions · Tier prici'!I6 -> 1189.5277 | L16: ='Monthly Financial Plan · Torque'!L8*'Torque Assumptions · Tier prici'!I6 -> 1511.4279 | M16: ='Monthly Financial Plan · Torque'!M8*'Torque Assumptions · Tier prici'!I6 -> 1912.5773
A17: Team | B17: ='Monthly Financial Plan · Torque'!B9*'Torque Assumptions · Tier prici'!I7 -> 79.875 | C17: ='Monthly Financial Plan · Torque'!C9*'Torque Assumptions · Tier prici'!I7 -> 177.3225 | D17: ='Monthly Financial Plan · Torque'!D9*'Torque Assumptions · Tier prici'!I7 -> 296.80751 | E17: ='Monthly Financial Plan · Torque'!E9*'Torque Assumptions · Tier prici'!I7 -> 443.90915 | F17: ='Monthly Financial Plan · Torque'!F9*'Torque Assumptions · Tier prici'!I7 -> 625.5992 | G17: ='Monthly Financial Plan · Torque'!G9*'Torque Assumptions · Tier prici'!I7 -> 850.59038 | H17: ='Monthly Financial Plan · Torque'!H9*'Torque Assumptions · Tier prici'!I7 -> 1129.7716 | I17: ='Monthly Financial Plan · Torque'!I9*'Torque Assumptions · Tier prici'!I7 -> 1476.7521 | J17: ='Monthly Financial Plan · Torque'!J9*'Torque Assumptions · Tier prici'!I7 -> 1908.5417 | K17: ='Monthly Financial Plan · Torque'!K9*'Torque Assumptions · Tier prici'!I7 -> 2446.4006 | L17: ='Monthly Financial Plan · Torque'!L9*'Torque Assumptions · Tier prici'!I7 -> 3116.9024 | M17: ='Monthly Financial Plan · Torque'!M9*'Torque Assumptions · Tier prici'!I7 -> 3953.2628
A18: Verified pull requests | B18: =SUM('Monthly Financial Plan · Torque'!B15,'Monthly Financial Plan · Torque'!B16,'Monthly Financial Plan · Torque'!B17)*'Torque Assumptions · Run cost a'!B17 -> 82.845 | C18: =SUM('Monthly Financial Plan · Torque'!C15,'Monthly Financial Plan · Torque'!C16,'Monthly Financial Plan · Torque'!C17)*'Torque Assumptions · Run cost a'!B17 -> 182.907 | D18: =SUM('Monthly Financial Plan · Torque'!D15,'Monthly Financial Plan · Torque'!D16,'Monthly Financial Plan · Torque'!D17)*'Torque Assumptions · Run cost a'!B17 -> 304.66105 | E18: =SUM('Monthly Financial Plan · Torque'!E15,'Monthly Financial Plan · Torque'!E16,'Monthly Financial Plan · Torque'!E17)*'Torque Assumptions · Run cost a'!B17 -> 453.69129 | F18: =SUM('Monthly Financial Plan · Torque'!F15,'Monthly Financial Plan · Torque'!F16,'Monthly Financial Plan · Torque'!F17)*'Torque Assumptions · Run cost a'!B17 -> 636.96885 | G18: =SUM('Monthly Financial Plan · Torque'!G15,'Monthly Financial Plan · Torque'!G16,'Monthly Financial Plan · Torque'!G17)*'Torque Assumptions · Run cost a'!B17 -> 863.19919 | H18: =SUM('Monthly Financial Plan · Torque'!H15,'Monthly Financial Plan · Torque'!H16,'Monthly Financial Plan · Torque'!H17)*'Torque Assumptions · Run cost a'!B17 -> 1143.2561 | I18: =SUM('Monthly Financial Plan · Torque'!I15,'Monthly Financial Plan · Torque'!I16,'Monthly Financial Plan · Torque'!I17)*'Torque Assumptions · Run cost a'!B17 -> 1490.7246 | J18: =SUM('Monthly Financial Plan · Torque'!J15,'Monthly Financial Plan · Torque'!J16,'Monthly Financial Plan · Torque'!J17)*'Torque Assumptions · Run cost a'!B17 -> 1922.5787 | K18: =SUM('Monthly Financial Plan · Torque'!K15,'Monthly Financial Plan · Torque'!K16,'Monthly Financial Plan · Torque'!K17)*'Torque Assumptions · Run cost a'!B17 -> 2460.0296 | L18: =SUM('Monthly Financial Plan · Torque'!L15,'Monthly Financial Plan · Torque'!L16,'Monthly Financial Plan · Torque'!L17)*'Torque Assumptions · Run cost a'!B17 -> 3129.5849 | M18: =SUM('Monthly Financial Plan · Torque'!M15,'Monthly Financial Plan · Torque'!M16,'Monthly Financial Plan · Torque'!M17)*'Torque Assumptions · Run cost a'!B17 -> 3964.3736
A19: Subscription revenue | B19: =SUM('Monthly Financial Plan · Torque'!B20,'Monthly Financial Plan · Torque'!B21,'Monthly Financial Plan · Torque'!B22) -> 327 | C19: =SUM('Monthly Financial Plan · Torque'!C20,'Monthly Financial Plan · Torque'!C21,'Monthly Financial Plan · Torque'!C22) -> 721.686 | D19: =SUM('Monthly Financial Plan · Torque'!D20,'Monthly Financial Plan · Torque'!D21,'Monthly Financial Plan · Torque'!D22) -> 1201.6794 | E19: =SUM('Monthly Financial Plan · Torque'!E20,'Monthly Financial Plan · Torque'!E21,'Monthly Financial Plan · Torque'!E22) -> 1788.9667 | F19: =SUM('Monthly Financial Plan · Torque'!F20,'Monthly Financial Plan · Torque'!F21,'Monthly Financial Plan · Torque'!F22) -> 2510.9937 | G19: =SUM('Monthly Financial Plan · Torque'!G20,'Monthly Financial Plan · Torque'!G21,'Monthly Financial Plan · Torque'!G22) -> 3402.0324 | H19: =SUM('Monthly Financial Plan · Torque'!H20,'Monthly Financial Plan · Torque'!H21,'Monthly Financial Plan · Torque'!H22) -> 4504.8899 | I19: =SUM('Monthly Financial Plan · Torque'!I20,'Monthly Financial Plan · Torque'!I21,'Monthly Financial Plan · Torque'!I22) -> 5873.0442 | ... M19: =SUM('Monthly Financial Plan · Torque'!M20,'Monthly Financial Plan · Torque'!M21,'Monthly Financial Plan · Torque'!M22) -> 15611.235
A20: Maintainer | B20: ='Monthly Financial Plan · Torque'!B7*'Torque Assumptions · Tier prici'!B5 -> 43.5 | C20: ='Monthly Financial Plan · Torque'!C7*'Torque Assumptions · Tier prici'!B5 -> 94.395 | D20: ='Monthly Financial Plan · Torque'!D7*'Torque Assumptions · Tier prici'!B5 -> 154.81215 | E20: ='Monthly Financial Plan · Torque'!E7*'Torque Assumptions · Tier prici'!B5 -> 227.38812 | F20: ='Monthly Financial Plan · Torque'!F7*'Torque Assumptions · Tier prici'!B5 -> 315.39824 | G20: ='Monthly Financial Plan · Torque'!G7*'Torque Assumptions · Tier prici'!B5 -> 422.91784 | H20: ='Monthly Financial Plan · Torque'!H7*'Torque Assumptions · Tier prici'!B5 -> 555.02375 | I20: ='Monthly Financial Plan · Torque'!I7*'Torque Assumptions · Tier prici'!B5 -> 718.04601 | J20: ='Monthly Financial Plan · Torque'!J7*'Torque Assumptions · Tier prici'!B5 -> 919.88254 | K20: ='Monthly Financial Plan · Torque'!K7*'Torque Assumptions · Tier prici'!B5 -> 1170.3922 | L20: ='Monthly Financial Plan · Torque'!L7*'Torque Assumptions · Tier prici'!B5 -> 1481.8861 | M20: ='Monthly Financial Plan · Torque'!M7*'Torque Assumptions · Tier prici'!B5 -> 1869.7419
A21: Starter | B21: ='Monthly Financial Plan · Torque'!B8*'Torque Assumptions · Tier prici'!B6 -> 103.95 | C21: ='Monthly Financial Plan · Torque'!C8*'Torque Assumptions · Tier prici'!B6 -> 228.69 | D21: ='Monthly Financial Plan · Torque'!D8*'Torque Assumptions · Tier prici'!B6 -> 379.67737 | E21: ='Monthly Financial Plan · Torque'!E8*'Torque Assumptions · Tier prici'!B6 -> 563.72085 | F21: ='Monthly Financial Plan · Torque'!F8*'Torque Assumptions · Tier prici'!B6 -> 789.31899 | G21: ='Monthly Financial Plan · Torque'!G8*'Torque Assumptions · Tier prici'!B6 -> 1067.0833 | H21: ='Monthly Financial Plan · Torque'!H8*'Torque Assumptions · Tier prici'!B6 -> 1410.2669 | I21: ='Monthly Financial Plan · Torque'!I8*'Torque Assumptions · Tier prici'!B6 -> 1835.4258 | J21: ='Monthly Financial Plan · Torque'!J8*'Torque Assumptions · Tier prici'!B6 -> 2363.2448 | K21: ='Monthly Financial Plan · Torque'!K8*'Torque Assumptions · Tier prici'!B6 -> 3019.5704 | L21: ='Monthly Financial Plan · Torque'!L8*'Torque Assumptions · Tier prici'!B6 -> 3836.7017 | M21: ='Monthly Financial Plan · Torque'!M8*'Torque Assumptions · Tier prici'!B6 -> 4855.0039
A22: Team | B22: ='Monthly Financial Plan · Torque'!B9*'Torque Assumptions · Tier prici'!B7 -> 179.55 | C22: ='Monthly Financial Plan · Torque'!C9*'Torque Assumptions · Tier prici'!B7 -> 398.601 | D22: ='Monthly Financial Plan · Torque'!D9*'Torque Assumptions · Tier prici'!B7 -> 667.18984 | E22: ='Monthly Financial Plan · Torque'!E9*'Torque Assumptions · Tier prici'!B7 -> 997.85774 | F22: ='Monthly Financial Plan · Torque'!F9*'Torque Assumptions · Tier prici'!B7 -> 1406.2765 | G22: ='Monthly Financial Plan · Torque'!G9*'Torque Assumptions · Tier prici'!B7 -> 1912.0313 | H22: ='Monthly Financial Plan · Torque'!H9*'Torque Assumptions · Tier prici'!B7 -> 2539.5993 | I22: ='Monthly Financial Plan · Torque'!I9*'Torque Assumptions · Tier prici'!B7 -> 3319.5724 | J22: ='Monthly Financial Plan · Torque'!J9*'Torque Assumptions · Tier prici'!B7 -> 4290.1866 | K22: ='Monthly Financial Plan · Torque'!K9*'Torque Assumptions · Tier prici'!B7 -> 5499.2328 | L22: ='Monthly Financial Plan · Torque'!L9*'Torque Assumptions · Tier prici'!B7 -> 7006.4455 | M22: ='Monthly Financial Plan · Torque'!M9*'Torque Assumptions · Tier prici'!B7 -> 8886.4892
A23: Overage revenue | B23: =SUM('Monthly Financial Plan · Torque'!B24,'Monthly Financial Plan · Torque'!B25,'Monthly Financial Plan · Torque'!B26) -> 22.4625 | C23: =SUM('Monthly Financial Plan · Torque'!C24,'Monthly Financial Plan · Torque'!C25,'Monthly Financial Plan · Torque'!C26) -> 49.63125 | D23: =SUM('Monthly Financial Plan · Torque'!D24,'Monthly Financial Plan · Torque'!D25,'Monthly Financial Plan · Torque'!D26) -> 82.724681 | E23: =SUM('Monthly Financial Plan · Torque'!E24,'Monthly Financial Plan · Torque'!E25,'Monthly Financial Plan · Torque'!E26) -> 123.26362 | F23: =SUM('Monthly Financial Plan · Torque'!F24,'Monthly Financial Plan · Torque'!F25,'Monthly Financial Plan · Torque'!F26) -> 173.14703 | G23: =SUM('Monthly Financial Plan · Torque'!G24,'Monthly Financial Plan · Torque'!G25,'Monthly Financial Plan · Torque'!G26) -> 234.74665 | H23: =SUM('Monthly Financial Plan · Torque'!H24,'Monthly Financial Plan · Torque'!H25,'Monthly Financial Plan · Torque'!H26) -> 311.02531 | I23: =SUM('Monthly Financial Plan · Torque'!I24,'Monthly Financial Plan · Torque'!I25,'Monthly Financial Plan · Torque'!I26) -> 405.68484 | ... M23: =SUM('Monthly Financial Plan · Torque'!M24,'Monthly Financial Plan · Torque'!M25,'Monthly Financial Plan · Torque'!M26) -> 1079.7724
A24: Maintainer | B24: ='Monthly Financial Plan · Torque'!B7*'Torque Assumptions · Tier prici'!F5*'Torque Assumptions · Tier prici'!D5 -> 1.875 | C24: ='Monthly Financial Plan · Torque'!C7*'Torque Assumptions · Tier prici'!F5*'Torque Assumptions · Tier prici'!D5 -> 4.06875 | D24: ='Monthly Financial Plan · Torque'!D7*'Torque Assumptions · Tier prici'!F5*'Torque Assumptions · Tier prici'!D5 -> 6.6729375 | E24: ='Monthly Financial Plan · Torque'!E7*'Torque Assumptions · Tier prici'!F5*'Torque Assumptions · Tier prici'!D5 -> 9.8012119 | F24: ='Monthly Financial Plan · Torque'!F7*'Torque Assumptions · Tier prici'!F5*'Torque Assumptions · Tier prici'!D5 -> 13.594752 | G24: ='Monthly Financial Plan · Torque'!G7*'Torque Assumptions · Tier prici'!F5*'Torque Assumptions · Tier prici'!D5 -> 18.229217 | H24: ='Monthly Financial Plan · Torque'!H7*'Torque Assumptions · Tier prici'!F5*'Torque Assumptions · Tier prici'!D5 -> 23.923437 | I24: ='Monthly Financial Plan · Torque'!I7*'Torque Assumptions · Tier prici'!F5*'Torque Assumptions · Tier prici'!D5 -> 30.950259 | J24: ='Monthly Financial Plan · Torque'!J7*'Torque Assumptions · Tier prici'!F5*'Torque Assumptions · Tier prici'!D5 -> 39.650109 | K24: ='Monthly Financial Plan · Torque'!K7*'Torque Assumptions · Tier prici'!F5*'Torque Assumptions · Tier prici'!D5 -> 50.447939 | L24: ='Monthly Financial Plan · Torque'!L7*'Torque Assumptions · Tier prici'!F5*'Torque Assumptions · Tier prici'!D5 -> 63.874402 | M24: ='Monthly Financial Plan · Torque'!M7*'Torque Assumptions · Tier prici'!F5*'Torque Assumptions · Tier prici'!D5 -> 80.592323
A25: Starter | B25: ='Monthly Financial Plan · Torque'!B8*'Torque Assumptions · Tier prici'!F6*'Torque Assumptions · Tier prici'!D6 -> 7.0875 | C25: ='Monthly Financial Plan · Torque'!C8*'Torque Assumptions · Tier prici'!F6*'Torque Assumptions · Tier prici'!D6 -> 15.5925 | D25: ='Monthly Financial Plan · Torque'!D8*'Torque Assumptions · Tier prici'!F6*'Torque Assumptions · Tier prici'!D6 -> 25.887094 | E25: ='Monthly Financial Plan · Torque'!E8*'Torque Assumptions · Tier prici'!F6*'Torque Assumptions · Tier prici'!D6 -> 38.435512 | F25: ='Monthly Financial Plan · Torque'!F8*'Torque Assumptions · Tier prici'!F6*'Torque Assumptions · Tier prici'!D6 -> 53.817204 | G25: ='Monthly Financial Plan · Torque'!G8*'Torque Assumptions · Tier prici'!F6*'Torque Assumptions · Tier prici'!D6 -> 72.755677 | H25: ='Monthly Financial Plan · Torque'!H8*'Torque Assumptions · Tier prici'!F6*'Torque Assumptions · Tier prici'!D6 -> 96.15456 | I25: ='Monthly Financial Plan · Torque'!I8*'Torque Assumptions · Tier prici'!F6*'Torque Assumptions · Tier prici'!D6 -> 125.14267 | J25: ='Monthly Financial Plan · Torque'!J8*'Torque Assumptions · Tier prici'!F6*'Torque Assumptions · Tier prici'!D6 -> 161.13032 | K25: ='Monthly Financial Plan · Torque'!K8*'Torque Assumptions · Tier prici'!F6*'Torque Assumptions · Tier prici'!D6 -> 205.8798 | L25: ='Monthly Financial Plan · Torque'!L8*'Torque Assumptions · Tier prici'!F6*'Torque Assumptions · Tier prici'!D6 -> 261.5933 | M25: ='Monthly Financial Plan · Torque'!M8*'Torque Assumptions · Tier prici'!F6*'Torque Assumptions · Tier prici'!D6 -> 331.02299
A26: Team | B26: ='Monthly Financial Plan · Torque'!B9*'Torque Assumptions · Tier prici'!F7*'Torque Assumptions · Tier prici'!D7 -> 13.5 | C26: ='Monthly Financial Plan · Torque'!C9*'Torque Assumptions · Tier prici'!F7*'Torque Assumptions · Tier prici'!D7 -> 29.97 | D26: ='Monthly Financial Plan · Torque'!D9*'Torque Assumptions · Tier prici'!F7*'Torque Assumptions · Tier prici'!D7 -> 50.16465 | E26: ='Monthly Financial Plan · Torque'!E9*'Torque Assumptions · Tier prici'!F7*'Torque Assumptions · Tier prici'!D7 -> 75.026898 | F26: ='Monthly Financial Plan · Torque'!F9*'Torque Assumptions · Tier prici'!F7*'Torque Assumptions · Tier prici'!D7 -> 105.73508 | G26: ='Monthly Financial Plan · Torque'!G9*'Torque Assumptions · Tier prici'!F7*'Torque Assumptions · Tier prici'!D7 -> 143.76175 | H26: ='Monthly Financial Plan · Torque'!H9*'Torque Assumptions · Tier prici'!F7*'Torque Assumptions · Tier prici'!D7 -> 190.94731 | I26: ='Monthly Financial Plan · Torque'!I9*'Torque Assumptions · Tier prici'!F7*'Torque Assumptions · Tier prici'!D7 -> 249.59191 | J26: ='Monthly Financial Plan · Torque'!J9*'Torque Assumptions · Tier prici'!F7*'Torque Assumptions · Tier prici'!D7 -> 322.57042 | K26: ='Monthly Financial Plan · Torque'!K9*'Torque Assumptions · Tier prici'!F7*'Torque Assumptions · Tier prici'!D7 -> 413.47615 | L26: ='Monthly Financial Plan · Torque'!L9*'Torque Assumptions · Tier prici'!F7*'Torque Assumptions · Tier prici'!D7 -> 526.80041 | M26: ='Monthly Financial Plan · Torque'!M9*'Torque Assumptions · Tier prici'!F7*'Torque Assumptions · Tier prici'!D7 -> 668.15708
A27: Total revenue | B27: =SUM('Monthly Financial Plan · Torque'!B20,'Monthly Financial Plan · Torque'!B21,'Monthly Financial Plan · Torque'!B22)+SUM('Monthly Financial Plan · Torque'!B24,'Monthly Financial Plan · Torque'!B25,'Monthly Financial Plan · Torque'!B26) -> 349.4625 | C27: =SUM('Monthly Financial Plan · Torque'!C20,'Monthly Financial Plan · Torque'!C21,'Monthly Financial Plan · Torque'!C22)+SUM('Monthly Financial Plan · Torque'!C24,'Monthly Financial Plan · Torque'!C25,'Monthly Financial Plan · Torque'!C26) -> 771.31725 | D27: =SUM('Monthly Financial Plan · Torque'!D20,'Monthly Financial Plan · Torque'!D21,'Monthly Financial Plan · Torque'!D22)+SUM('Monthly Financial Plan · Torque'!D24,'Monthly Financial Plan · Torque'!D25,'Monthly Financial Plan · Torque'!D26) -> 1284.4041 | E27: =SUM('Monthly Financial Plan · Torque'!E20,'Monthly Financial Plan · Torque'!E21,'Monthly Financial Plan · Torque'!E22)+SUM('Monthly Financial Plan · Torque'!E24,'Monthly Financial Plan · Torque'!E25,'Monthly Financial Plan · Torque'!E26) -> 1912.2303 | F27: =SUM('Monthly Financial Plan · Torque'!F20,'Monthly Financial Plan · Torque'!F21,'Monthly Financial Plan · Torque'!F22)+SUM('Monthly Financial Plan · Torque'!F24,'Monthly Financial Plan · Torque'!F25,'Monthly Financial Plan · Torque'!F26) -> 2684.1408 | G27: =SUM('Monthly Financial Plan · Torque'!G20,'Monthly Financial Plan · Torque'!G21,'Monthly Financial Plan · Torque'!G22)+SUM('Monthly Financial Plan · Torque'!G24,'Monthly Financial Plan · Torque'!G25,'Monthly Financial Plan · Torque'!G26) -> 3636.7791 | H27: =SUM('Monthly Financial Plan · Torque'!H20,'Monthly Financial Plan · Torque'!H21,'Monthly Financial Plan · Torque'!H22)+SUM('Monthly Financial Plan · Torque'!H24,'Monthly Financial Plan · Torque'!H25,'Monthly Financial Plan · Torque'!H26) -> 4815.9152 | I27: =SUM('Monthly Financial Plan · Torque'!I20,'Monthly Financial Plan · Torque'!I21,'Monthly Financial Plan · Torque'!I22)+SUM('Monthly Financial Plan · Torque'!I24,'Monthly Financial Plan · Torque'!I25,'Monthly Financial Plan · Torque'!I26) -> 6278.729 | ... M27: =SUM('Monthly Financial Plan · Torque'!M20,'Monthly Financial Plan · Torque'!M21,'Monthly Financial Plan · Torque'!M22)+SUM('Monthly Financial Plan · Torque'!M24,'Monthly Financial Plan · Torque'!M25,'Monthly Financial Plan · Torque'!M26) -> 16691.007
A28: LLM token cost | B28: =SUM('Monthly Financial Plan · Torque'!B15,'Monthly Financial Plan · Torque'!B16,'Monthly Financial Plan · Torque'!B17)*'Unit Economics & Sensitivity ·'!B8 -> 134.62312 | C28: =SUM('Monthly Financial Plan · Torque'!C15,'Monthly Financial Plan · Torque'!C16,'Monthly Financial Plan · Torque'!C17)*'Unit Economics & Sensitivity ·'!B8 -> 297.22388 | D28: =SUM('Monthly Financial Plan · Torque'!D15,'Monthly Financial Plan · Torque'!D16,'Monthly Financial Plan · Torque'!D17)*'Unit Economics & Sensitivity ·'!B8 -> 495.0742 | E28: =SUM('Monthly Financial Plan · Torque'!E15,'Monthly Financial Plan · Torque'!E16,'Monthly Financial Plan · Torque'!E17)*'Unit Economics & Sensitivity ·'!B8 -> 737.24834 | F28: =SUM('Monthly Financial Plan · Torque'!F15,'Monthly Financial Plan · Torque'!F16,'Monthly Financial Plan · Torque'!F17)*'Unit Economics & Sensitivity ·'!B8 -> 1035.0744 | G28: =SUM('Monthly Financial Plan · Torque'!G15,'Monthly Financial Plan · Torque'!G16,'Monthly Financial Plan · Torque'!G17)*'Unit Economics & Sensitivity ·'!B8 -> 1402.6987 | H28: =SUM('Monthly Financial Plan · Torque'!H15,'Monthly Financial Plan · Torque'!H16,'Monthly Financial Plan · Torque'!H17)*'Unit Economics & Sensitivity ·'!B8 -> 1857.7912 | I28: =SUM('Monthly Financial Plan · Torque'!I15,'Monthly Financial Plan · Torque'!I16,'Monthly Financial Plan · Torque'!I17)*'Unit Economics & Sensitivity ·'!B8 -> 2422.4275 | J28: =SUM('Monthly Financial Plan · Torque'!J15,'Monthly Financial Plan · Torque'!J16,'Monthly Financial Plan · Torque'!J17)*'Unit Economics & Sensitivity ·'!B8 -> 3124.1904 | K28: =SUM('Monthly Financial Plan · Torque'!K15,'Monthly Financial Plan · Torque'!K16,'Monthly Financial Plan · Torque'!K17)*'Unit Economics & Sensitivity ·'!B8 -> 3997.5481 | L28: =SUM('Monthly Financial Plan · Torque'!L15,'Monthly Financial Plan · Torque'!L16,'Monthly Financial Plan · Torque'!L17)*'Unit Economics & Sensitivity ·'!B8 -> 5085.5755 | M28: =SUM('Monthly Financial Plan · Torque'!M15,'Monthly Financial Plan · Torque'!M16,'Monthly Financial Plan · Torque'!M17)*'Unit Economics & Sensitivity ·'!B8 -> 6442.1072
A29: Sandbox compute cost | B29: =SUM('Monthly Financial Plan · Torque'!B15,'Monthly Financial Plan · Torque'!B16,'Monthly Financial Plan · Torque'!B17)*'Unit Economics & Sensitivity ·'!B9 -> 10.76985 | C29: =SUM('Monthly Financial Plan · Torque'!C15,'Monthly Financial Plan · Torque'!C16,'Monthly Financial Plan · Torque'!C17)*'Unit Economics & Sensitivity ·'!B9 -> 23.77791 | D29: =SUM('Monthly Financial Plan · Torque'!D15,'Monthly Financial Plan · Torque'!D16,'Monthly Financial Plan · Torque'!D17)*'Unit Economics & Sensitivity ·'!B9 -> 39.605936 | E29: =SUM('Monthly Financial Plan · Torque'!E15,'Monthly Financial Plan · Torque'!E16,'Monthly Financial Plan · Torque'!E17)*'Unit Economics & Sensitivity ·'!B9 -> 58.979867 | F29: =SUM('Monthly Financial Plan · Torque'!F15,'Monthly Financial Plan · Torque'!F16,'Monthly Financial Plan · Torque'!F17)*'Unit Economics & Sensitivity ·'!B9 -> 82.805951 | G29: =SUM('Monthly Financial Plan · Torque'!G15,'Monthly Financial Plan · Torque'!G16,'Monthly Financial Plan · Torque'!G17)*'Unit Economics & Sensitivity ·'!B9 -> 112.21589 | H29: =SUM('Monthly Financial Plan · Torque'!H15,'Monthly Financial Plan · Torque'!H16,'Monthly Financial Plan · Torque'!H17)*'Unit Economics & Sensitivity ·'!B9 -> 148.6233 | I29: =SUM('Monthly Financial Plan · Torque'!I15,'Monthly Financial Plan · Torque'!I16,'Monthly Financial Plan · Torque'!I17)*'Unit Economics & Sensitivity ·'!B9 -> 193.7942 | J29: =SUM('Monthly Financial Plan · Torque'!J15,'Monthly Financial Plan · Torque'!J16,'Monthly Financial Plan · Torque'!J17)*'Unit Economics & Sensitivity ·'!B9 -> 249.93524 | K29: =SUM('Monthly Financial Plan · Torque'!K15,'Monthly Financial Plan · Torque'!K16,'Monthly Financial Plan · Torque'!K17)*'Unit Economics & Sensitivity ·'!B9 -> 319.80385 | L29: =SUM('Monthly Financial Plan · Torque'!L15,'Monthly Financial Plan · Torque'!L16,'Monthly Financial Plan · Torque'!L17)*'Unit Economics & Sensitivity ·'!B9 -> 406.84604 | M29: =SUM('Monthly Financial Plan · Torque'!M15,'Monthly Financial Plan · Torque'!M16,'Monthly Financial Plan · Torque'!M17)*'Unit Economics & Sensitivity ·'!B9 -> 515.36857
A30: Observability and context cost | B30: =SUM('Monthly Financial Plan · Torque'!B15,'Monthly Financial Plan · Torque'!B16,'Monthly Financial Plan · Torque'!B17)*('Torque Assumptions · Run cost a'!B14+'Torque Assumptions · Run cost a'!B15) -> 2.7615 | C30: =SUM('Monthly Financial Plan · Torque'!C15,'Monthly Financial Plan · Torque'!C16,'Monthly Financial Plan · Torque'!C17)*('Torque Assumptions · Run cost a'!B14+'Torque Assumptions · Run cost a'!B15) -> 6.0969 | D30: =SUM('Monthly Financial Plan · Torque'!D15,'Monthly Financial Plan · Torque'!D16,'Monthly Financial Plan · Torque'!D17)*('Torque Assumptions · Run cost a'!B14+'Torque Assumptions · Run cost a'!B15) -> 10.155368 | E30: =SUM('Monthly Financial Plan · Torque'!E15,'Monthly Financial Plan · Torque'!E16,'Monthly Financial Plan · Torque'!E17)*('Torque Assumptions · Run cost a'!B14+'Torque Assumptions · Run cost a'!B15) -> 15.123043 | F30: =SUM('Monthly Financial Plan · Torque'!F15,'Monthly Financial Plan · Torque'!F16,'Monthly Financial Plan · Torque'!F17)*('Torque Assumptions · Run cost a'!B14+'Torque Assumptions · Run cost a'!B15) -> 21.232295 | G30: =SUM('Monthly Financial Plan · Torque'!G15,'Monthly Financial Plan · Torque'!G16,'Monthly Financial Plan · Torque'!G17)*('Torque Assumptions · Run cost a'!B14+'Torque Assumptions · Run cost a'!B15) -> 28.773306 | H30: =SUM('Monthly Financial Plan · Torque'!H15,'Monthly Financial Plan · Torque'!H16,'Monthly Financial Plan · Torque'!H17)*('Torque Assumptions · Run cost a'!B14+'Torque Assumptions · Run cost a'!B15) -> 38.108538 | I30: =SUM('Monthly Financial Plan · Torque'!I15,'Monthly Financial Plan · Torque'!I16,'Monthly Financial Plan · Torque'!I17)*('Torque Assumptions · Run cost a'!B14+'Torque Assumptions · Run cost a'!B15) -> 49.690821 | J30: =SUM('Monthly Financial Plan · Torque'!J15,'Monthly Financial Plan · Torque'!J16,'Monthly Financial Plan · Torque'!J17)*('Torque Assumptions · Run cost a'!B14+'Torque Assumptions · Run cost a'!B15) -> 64.085958 | K30: =SUM('Monthly Financial Plan · Torque'!K15,'Monthly Financial Plan · Torque'!K16,'Monthly Financial Plan · Torque'!K17)*('Torque Assumptions · Run cost a'!B14+'Torque Assumptions · Run cost a'!B15) -> 82.000986 | L30: =SUM('Monthly Financial Plan · Torque'!L15,'Monthly Financial Plan · Torque'!L16,'Monthly Financial Plan · Torque'!L17)*('Torque Assumptions · Run cost a'!B14+'Torque Assumptions · Run cost a'!B15) -> 104.3195 | M30: =SUM('Monthly Financial Plan · Torque'!M15,'Monthly Financial Plan · Torque'!M16,'Monthly Financial Plan · Torque'!M17)*('Torque Assumptions · Run cost a'!B14+'Torque Assumptions · Run cost a'!B15) -> 132.14579
A31: Storage cost | B31: =SUM('Monthly Financial Plan · Torque'!B15,'Monthly Financial Plan · Torque'!B16,'Monthly Financial Plan · Torque'!B17)*'Torque Assumptions · Run cost a'!B16 -> 0.690375 | C31: =SUM('Monthly Financial Plan · Torque'!C15,'Monthly Financial Plan · Torque'!C16,'Monthly Financial Plan · Torque'!C17)*'Torque Assumptions · Run cost a'!B16 -> 1.524225 | D31: =SUM('Monthly Financial Plan · Torque'!D15,'Monthly Financial Plan · Torque'!D16,'Monthly Financial Plan · Torque'!D17)*'Torque Assumptions · Run cost a'!B16 -> 2.5388421 | E31: =SUM('Monthly Financial Plan · Torque'!E15,'Monthly Financial Plan · Torque'!E16,'Monthly Financial Plan · Torque'!E17)*'Torque Assumptions · Run cost a'!B16 -> 3.7807607 | F31: =SUM('Monthly Financial Plan · Torque'!F15,'Monthly Financial Plan · Torque'!F16,'Monthly Financial Plan · Torque'!F17)*'Torque Assumptions · Run cost a'!B16 -> 5.3080738 | G31: =SUM('Monthly Financial Plan · Torque'!G15,'Monthly Financial Plan · Torque'!G16,'Monthly Financial Plan · Torque'!G17)*'Torque Assumptions · Run cost a'!B16 -> 7.1933265 | H31: =SUM('Monthly Financial Plan · Torque'!H15,'Monthly Financial Plan · Torque'!H16,'Monthly Financial Plan · Torque'!H17)*'Torque Assumptions · Run cost a'!B16 -> 9.5271346 | I31: =SUM('Monthly Financial Plan · Torque'!I15,'Monthly Financial Plan · Torque'!I16,'Monthly Financial Plan · Torque'!I17)*'Torque Assumptions · Run cost a'!B16 -> 12.422705 | J31: =SUM('Monthly Financial Plan · Torque'!J15,'Monthly Financial Plan · Torque'!J16,'Monthly Financial Plan · Torque'!J17)*'Torque Assumptions · Run cost a'!B16 -> 16.021489 | K31: =SUM('Monthly Financial Plan · Torque'!K15,'Monthly Financial Plan · Torque'!K16,'Monthly Financial Plan · Torque'!K17)*'Torque Assumptions · Run cost a'!B16 -> 20.500247 | L31: =SUM('Monthly Financial Plan · Torque'!L15,'Monthly Financial Plan · Torque'!L16,'Monthly Financial Plan · Torque'!L17)*'Torque Assumptions · Run cost a'!B16 -> 26.079874 | M31: =SUM('Monthly Financial Plan · Torque'!M15,'Monthly Financial Plan · Torque'!M16,'Monthly Financial Plan · Torque'!M17)*'Torque Assumptions · Run cost a'!B16 -> 33.036447
A32: Hosting cost | B32: =IF('Torque Assumptions · Growth & o'!B7="","",'Torque Assumptions · Growth & o'!B7) -> 150 | C32: =IF('Torque Assumptions · Growth & o'!B7="","",'Torque Assumptions · Growth & o'!B7) -> 150 | D32: =IF('Torque Assumptions · Growth & o'!B7="","",'Torque Assumptions · Growth & o'!B7) -> 150 | E32: =IF('Torque Assumptions · Growth & o'!B7="","",'Torque Assumptions · Growth & o'!B7) -> 150 | F32: =IF('Torque Assumptions · Growth & o'!B7="","",'Torque Assumptions · Growth & o'!B7) -> 150 | G32: =IF('Torque Assumptions · Growth & o'!B7="","",'Torque Assumptions · Growth & o'!B7) -> 150 | H32: =IF('Torque Assumptions · Growth & o'!B7="","",'Torque Assumptions · Growth & o'!B7) -> 150 | I32: =IF('Torque Assumptions · Growth & o'!B7="","",'Torque Assumptions · Growth & o'!B7) -> 150 | J32: =IF('Torque Assumptions · Growth & o'!B7="","",'Torque Assumptions · Growth & o'!B7) -> 150 | K32: =IF('Torque Assumptions · Growth & o'!B7="","",'Torque Assumptions · Growth & o'!B7) -> 150 | L32: =IF('Torque Assumptions · Growth & o'!B7="","",'Torque Assumptions · Growth & o'!B7) -> 150 | M32: =IF('Torque Assumptions · Growth & o'!B7="","",'Torque Assumptions · Growth & o'!B7) -> 150
A33: Payment processing cost | B33: ='Monthly Financial Plan · Torque'!B27*'Torque Assumptions · Growth & o'!B13+SUM('Monthly Financial Plan · Torque'!B7,'Monthly Financial Plan · Torque'!B8,'Monthly Financial Plan · Torque'!B9)*'Torque Assumptions · Growth & o'!B14 -> 11.034413 | C33: ='Monthly Financial Plan · Torque'!C27*'Torque Assumptions · Growth & o'!B13+SUM('Monthly Financial Plan · Torque'!C7,'Monthly Financial Plan · Torque'!C8,'Monthly Financial Plan · Torque'!C9)*'Torque Assumptions · Growth & o'!B14 -> 24.3374 | D33: ='Monthly Financial Plan · Torque'!D27*'Torque Assumptions · Growth & o'!B13+SUM('Monthly Financial Plan · Torque'!D7,'Monthly Financial Plan · Torque'!D8,'Monthly Financial Plan · Torque'!D9)*'Torque Assumptions · Growth & o'!B14 -> 40.501406 | E33: ='Monthly Financial Plan · Torque'!E27*'Torque Assumptions · Growth & o'!B13+SUM('Monthly Financial Plan · Torque'!E7,'Monthly Financial Plan · Torque'!E8,'Monthly Financial Plan · Torque'!E9)*'Torque Assumptions · Growth & o'!B14 -> 60.265484 | F33: ='Monthly Financial Plan · Torque'!F27*'Torque Assumptions · Growth & o'!B13+SUM('Monthly Financial Plan · Torque'!F7,'Monthly Financial Plan · Torque'!F8,'Monthly Financial Plan · Torque'!F9)*'Torque Assumptions · Growth & o'!B14 -> 84.552049 | G33: ='Monthly Financial Plan · Torque'!G27*'Torque Assumptions · Growth & o'!B13+SUM('Monthly Financial Plan · Torque'!G7,'Monthly Financial Plan · Torque'!G8,'Monthly Financial Plan · Torque'!G9)*'Torque Assumptions · Growth & o'!B14 -> 114.51281 | H33: ='Monthly Financial Plan · Torque'!H27*'Torque Assumptions · Growth & o'!B13+SUM('Monthly Financial Plan · Torque'!H7,'Monthly Financial Plan · Torque'!H8,'Monthly Financial Plan · Torque'!H9)*'Torque Assumptions · Growth & o'!B14 -> 151.58618 | I33: ='Monthly Financial Plan · Torque'!I27*'Torque Assumptions · Growth & o'!B13+SUM('Monthly Financial Plan · Torque'!I7,'Monthly Financial Plan · Torque'!I8,'Monthly Financial Plan · Torque'!I9)*'Torque Assumptions · Growth & o'!B14 -> 197.56902 | J33: ='Monthly Financial Plan · Torque'!J27*'Torque Assumptions · Growth & o'!B13+SUM('Monthly Financial Plan · Torque'!J7,'Monthly Financial Plan · Torque'!J8,'Monthly Financial Plan · Torque'!J9)*'Torque Assumptions · Growth & o'!B14 -> 254.70636 | K33: ='Monthly Financial Plan · Torque'!K27*'Torque Assumptions · Growth & o'!B13+SUM('Monthly Financial Plan · Torque'!K7,'Monthly Financial Plan · Torque'!K8,'Monthly Financial Plan · Torque'!K9)*'Torque Assumptions · Growth & o'!B14 -> 325.80346 | L33: ='Monthly Financial Plan · Torque'!L27*'Torque Assumptions · Growth & o'!B13+SUM('Monthly Financial Plan · Torque'!L7,'Monthly Financial Plan · Torque'!L8,'Monthly Financial Plan · Torque'!L9)*'Torque Assumptions · Growth & o'!B14 -> 414.36597 | M33: ='Monthly Financial Plan · Torque'!M27*'Torque Assumptions · Growth & o'!B13+SUM('Monthly Financial Plan · Torque'!M7,'Monthly Financial Plan · Torque'!M8,'Monthly Financial Plan · Torque'!M9)*'Torque Assumptions · Growth & o'!B14 -> 524.77508
A34: Cost of revenue | B34: ='Monthly Financial Plan · Torque'!B28+'Monthly Financial Plan · Torque'!B29+'Monthly Financial Plan · Torque'!B30+'Monthly Financial Plan · Torque'!B31+'Monthly Financial Plan · Torque'!B32+'Monthly Financial Plan · Torque'!B33 -> 309.87926 | C34: ='Monthly Financial Plan · Torque'!C28+'Monthly Financial Plan · Torque'!C29+'Monthly Financial Plan · Torque'!C30+'Monthly Financial Plan · Torque'!C31+'Monthly Financial Plan · Torque'!C32+'Monthly Financial Plan · Torque'!C33 -> 502.96031 | D34: ='Monthly Financial Plan · Torque'!D28+'Monthly Financial Plan · Torque'!D29+'Monthly Financial Plan · Torque'!D30+'Monthly Financial Plan · Torque'!D31+'Monthly Financial Plan · Torque'!D32+'Monthly Financial Plan · Torque'!D33 -> 737.87576 | E34: ='Monthly Financial Plan · Torque'!E28+'Monthly Financial Plan · Torque'!E29+'Monthly Financial Plan · Torque'!E30+'Monthly Financial Plan · Torque'!E31+'Monthly Financial Plan · Torque'!E32+'Monthly Financial Plan · Torque'!E33 -> 1025.3975 | F34: ='Monthly Financial Plan · Torque'!F28+'Monthly Financial Plan · Torque'!F29+'Monthly Financial Plan · Torque'!F30+'Monthly Financial Plan · Torque'!F31+'Monthly Financial Plan · Torque'!F32+'Monthly Financial Plan · Torque'!F33 -> 1378.9728 | G34: ='Monthly Financial Plan · Torque'!G28+'Monthly Financial Plan · Torque'!G29+'Monthly Financial Plan · Torque'!G30+'Monthly Financial Plan · Torque'!G31+'Monthly Financial Plan · Torque'!G32+'Monthly Financial Plan · Torque'!G33 -> 1815.394 | H34: ='Monthly Financial Plan · Torque'!H28+'Monthly Financial Plan · Torque'!H29+'Monthly Financial Plan · Torque'!H30+'Monthly Financial Plan · Torque'!H31+'Monthly Financial Plan · Torque'!H32+'Monthly Financial Plan · Torque'!H33 -> 2355.6364 | I34: ='Monthly Financial Plan · Torque'!I28+'Monthly Financial Plan · Torque'!I29+'Monthly Financial Plan · Torque'!I30+'Monthly Financial Plan · Torque'!I31+'Monthly Financial Plan · Torque'!I32+'Monthly Financial Plan · Torque'!I33 -> 3025.9043 | ... M34: ='Monthly Financial Plan · Torque'!M28+'Monthly Financial Plan · Torque'!M29+'Monthly Financial Plan · Torque'!M30+'Monthly Financial Plan · Torque'!M31+'Monthly Financial Plan · Torque'!M32+'Monthly Financial Plan · Torque'!M33 -> 7797.433
A35: Gross profit before credits | B35: ='Monthly Financial Plan · Torque'!B27-'Monthly Financial Plan · Torque'!B34 -> 39.583237 | C35: ='Monthly Financial Plan · Torque'!C27-'Monthly Financial Plan · Torque'!C34 -> 268.35694 | D35: ='Monthly Financial Plan · Torque'!D27-'Monthly Financial Plan · Torque'!D34 -> 546.5283 | E35: ='Monthly Financial Plan · Torque'!E27-'Monthly Financial Plan · Torque'!E34 -> 886.83283 | F35: ='Monthly Financial Plan · Torque'!F27-'Monthly Financial Plan · Torque'!F34 -> 1305.168 | G35: ='Monthly Financial Plan · Torque'!G27-'Monthly Financial Plan · Torque'!G34 -> 1821.3851 | H35: ='Monthly Financial Plan · Torque'!H27-'Monthly Financial Plan · Torque'!H34 -> 2460.2788 | I35: ='Monthly Financial Plan · Torque'!I27-'Monthly Financial Plan · Torque'!I34 -> 3252.8248 | ... M35: ='Monthly Financial Plan · Torque'!M27-'Monthly Financial Plan · Torque'!M34 -> 8893.5743
A36: Gross margin before credits | B36: =IFERROR('Monthly Financial Plan · Torque'!B35/'Monthly Financial Plan · Torque'!B27,"") -> 0.11326891 | C36: =IFERROR('Monthly Financial Plan · Torque'!C35/'Monthly Financial Plan · Torque'!C27,"") -> 0.34792031 | D36: =IFERROR('Monthly Financial Plan · Torque'!D35/'Monthly Financial Plan · Torque'!D27,"") -> 0.42551119 | E36: =IFERROR('Monthly Financial Plan · Torque'!E35/'Monthly Financial Plan · Torque'!E27,"") -> 0.46376884 | F36: =IFERROR('Monthly Financial Plan · Torque'!F35/'Monthly Financial Plan · Torque'!F27,"") -> 0.4862517 | G36: =IFERROR('Monthly Financial Plan · Torque'!G35/'Monthly Financial Plan · Torque'!G27,"") -> 0.50082368 | H36: =IFERROR('Monthly Financial Plan · Torque'!H35/'Monthly Financial Plan · Torque'!H27,"") -> 0.51086423 | I36: =IFERROR('Monthly Financial Plan · Torque'!I35/'Monthly Financial Plan · Torque'!I27,"") -> 0.51807058 | ... M36: =IFERROR('Monthly Financial Plan · Torque'!M35/'Monthly Financial Plan · Torque'!M27,"") -> 0.53283628
A37: Hackathon credits available | B37: =45 -> 45 | C37: =0 -> 0 | D37: =0 -> 0 | E37: 0 | F37: 0 | G37: 0 | H37: 0 | I37: 0 | J37: 0 | K37: 0 | L37: 0 | M37: 0
A38: Hackathon credits applied | B38: =MIN('Monthly Financial Plan · Torque'!B37,'Monthly Financial Plan · Torque'!B28+'Monthly Financial Plan · Torque'!B29) -> 45 | C38: =MIN('Monthly Financial Plan · Torque'!C37,'Monthly Financial Plan · Torque'!C28+'Monthly Financial Plan · Torque'!C29) -> 0 | D38: =MIN('Monthly Financial Plan · Torque'!D37,'Monthly Financial Plan · Torque'!D28+'Monthly Financial Plan · Torque'!D29) -> 0 | E38: =MIN('Monthly Financial Plan · Torque'!E37,'Monthly Financial Plan · Torque'!E28+'Monthly Financial Plan · Torque'!E29) -> 0 | F38: =MIN('Monthly Financial Plan · Torque'!F37,'Monthly Financial Plan · Torque'!F28+'Monthly Financial Plan · Torque'!F29) -> 0 | G38: =MIN('Monthly Financial Plan · Torque'!G37,'Monthly Financial Plan · Torque'!G28+'Monthly Financial Plan · Torque'!G29) -> 0 | H38: =MIN('Monthly Financial Plan · Torque'!H37,'Monthly Financial Plan · Torque'!H28+'Monthly Financial Plan · Torque'!H29) -> 0 | I38: =MIN('Monthly Financial Plan · Torque'!I37,'Monthly Financial Plan · Torque'!I28+'Monthly Financial Plan · Torque'!I29) -> 0 | ... M38: =MIN('Monthly Financial Plan · Torque'!M37,'Monthly Financial Plan · Torque'!M28+'Monthly Financial Plan · Torque'!M29) -> 0
A39: Gross profit after credits | B39: ='Monthly Financial Plan · Torque'!B35+'Monthly Financial Plan · Torque'!B38 -> 84.583237 | C39: ='Monthly Financial Plan · Torque'!C35+'Monthly Financial Plan · Torque'!C38 -> 268.35694 | D39: ='Monthly Financial Plan · Torque'!D35+'Monthly Financial Plan · Torque'!D38 -> 546.5283 | E39: ='Monthly Financial Plan · Torque'!E35+'Monthly Financial Plan · Torque'!E38 -> 886.83283 | F39: ='Monthly Financial Plan · Torque'!F35+'Monthly Financial Plan · Torque'!F38 -> 1305.168 | G39: ='Monthly Financial Plan · Torque'!G35+'Monthly Financial Plan · Torque'!G38 -> 1821.3851 | H39: ='Monthly Financial Plan · Torque'!H35+'Monthly Financial Plan · Torque'!H38 -> 2460.2788 | I39: ='Monthly Financial Plan · Torque'!I35+'Monthly Financial Plan · Torque'!I38 -> 3252.8248 | ... M39: ='Monthly Financial Plan · Torque'!M35+'Monthly Financial Plan · Torque'!M38 -> 8893.5743
A40: Gross margin after credits | B40: =IFERROR('Monthly Financial Plan · Torque'!B39/'Monthly Financial Plan · Torque'!B27,"") -> 0.24203809 | C40: =IFERROR('Monthly Financial Plan · Torque'!C39/'Monthly Financial Plan · Torque'!C27,"") -> 0.34792031 | D40: =IFERROR('Monthly Financial Plan · Torque'!D39/'Monthly Financial Plan · Torque'!D27,"") -> 0.42551119 | E40: =IFERROR('Monthly Financial Plan · Torque'!E39/'Monthly Financial Plan · Torque'!E27,"") -> 0.46376884 | F40: =IFERROR('Monthly Financial Plan · Torque'!F39/'Monthly Financial Plan · Torque'!F27,"") -> 0.4862517 | G40: =IFERROR('Monthly Financial Plan · Torque'!G39/'Monthly Financial Plan · Torque'!G27,"") -> 0.50082368 | H40: =IFERROR('Monthly Financial Plan · Torque'!H39/'Monthly Financial Plan · Torque'!H27,"") -> 0.51086423 | I40: =IFERROR('Monthly Financial Plan · Torque'!I39/'Monthly Financial Plan · Torque'!I27,"") -> 0.51807058 | ... M40: =IFERROR('Monthly Financial Plan · Torque'!M39/'Monthly Financial Plan · Torque'!M27,"") -> 0.53283628
A41: Team expenses | B41: =IF('Torque Assumptions · Growth & o'!B10="","",'Torque Assumptions · Growth & o'!B10) -> 0 | C41: =IF('Torque Assumptions · Growth & o'!B10="","",'Torque Assumptions · Growth & o'!B10) -> 0 | D41: =IF('Torque Assumptions · Growth & o'!B10="","",'Torque Assumptions · Growth & o'!B10) -> 0 | E41: =IF('Torque Assumptions · Growth & o'!B10="","",'Torque Assumptions · Growth & o'!B10) -> 0 | F41: =IF('Torque Assumptions · Growth & o'!B10="","",'Torque Assumptions · Growth & o'!B10) -> 0 | G41: =IF('Torque Assumptions · Growth & o'!B10="","",'Torque Assumptions · Growth & o'!B10) -> 0 | H41: =IF('Torque Assumptions · Growth & o'!B10="","",'Torque Assumptions · Growth & o'!B10) -> 0 | I41: =IF('Torque Assumptions · Growth & o'!B10="","",'Torque Assumptions · Growth & o'!B10) -> 0 | J41: =IF('Torque Assumptions · Growth & o'!B10="","",'Torque Assumptions · Growth & o'!B10) -> 0 | K41: =IF('Torque Assumptions · Growth & o'!B10="","",'Torque Assumptions · Growth & o'!B10) -> 0 | L41: =IF('Torque Assumptions · Growth & o'!B10="","",'Torque Assumptions · Growth & o'!B10) -> 0 | M41: =IF('Torque Assumptions · Growth & o'!B10="","",'Torque Assumptions · Growth & o'!B10) -> 0
A42: Software and tools | B42: =IF('Torque Assumptions · Growth & o'!B8="","",'Torque Assumptions · Growth & o'!B8) -> 200 | C42: =IF('Torque Assumptions · Growth & o'!B8="","",'Torque Assumptions · Growth & o'!B8) -> 200 | D42: =IF('Torque Assumptions · Growth & o'!B8="","",'Torque Assumptions · Growth & o'!B8) -> 200 | E42: =IF('Torque Assumptions · Growth & o'!B8="","",'Torque Assumptions · Growth & o'!B8) -> 200 | F42: =IF('Torque Assumptions · Growth & o'!B8="","",'Torque Assumptions · Growth & o'!B8) -> 200 | G42: =IF('Torque Assumptions · Growth & o'!B8="","",'Torque Assumptions · Growth & o'!B8) -> 200 | H42: =IF('Torque Assumptions · Growth & o'!B8="","",'Torque Assumptions · Growth & o'!B8) -> 200 | I42: =IF('Torque Assumptions · Growth & o'!B8="","",'Torque Assumptions · Growth & o'!B8) -> 200 | J42: =IF('Torque Assumptions · Growth & o'!B8="","",'Torque Assumptions · Growth & o'!B8) -> 200 | K42: =IF('Torque Assumptions · Growth & o'!B8="","",'Torque Assumptions · Growth & o'!B8) -> 200 | L42: =IF('Torque Assumptions · Growth & o'!B8="","",'Torque Assumptions · Growth & o'!B8) -> 200 | M42: =IF('Torque Assumptions · Growth & o'!B8="","",'Torque Assumptions · Growth & o'!B8) -> 200
A43: Marketing | B43: =IF('Torque Assumptions · Growth & o'!B9="","",'Torque Assumptions · Growth & o'!B9) -> 500 | C43: =IF('Torque Assumptions · Growth & o'!B9="","",'Torque Assumptions · Growth & o'!B9) -> 500 | D43: =IF('Torque Assumptions · Growth & o'!B9="","",'Torque Assumptions · Growth & o'!B9) -> 500 | E43: =IF('Torque Assumptions · Growth & o'!B9="","",'Torque Assumptions · Growth & o'!B9) -> 500 | F43: =IF('Torque Assumptions · Growth & o'!B9="","",'Torque Assumptions · Growth & o'!B9) -> 500 | G43: =IF('Torque Assumptions · Growth & o'!B9="","",'Torque Assumptions · Growth & o'!B9) -> 500 | H43: =IF('Torque Assumptions · Growth & o'!B9="","",'Torque Assumptions · Growth & o'!B9) -> 500 | I43: =IF('Torque Assumptions · Growth & o'!B9="","",'Torque Assumptions · Growth & o'!B9) -> 500 | J43: =IF('Torque Assumptions · Growth & o'!B9="","",'Torque Assumptions · Growth & o'!B9) -> 500 | K43: =IF('Torque Assumptions · Growth & o'!B9="","",'Torque Assumptions · Growth & o'!B9) -> 500 | L43: =IF('Torque Assumptions · Growth & o'!B9="","",'Torque Assumptions · Growth & o'!B9) -> 500 | M43: =IF('Torque Assumptions · Growth & o'!B9="","",'Torque Assumptions · Growth & o'!B9) -> 500
A44: Operating expenses | B44: ='Monthly Financial Plan · Torque'!B41+'Monthly Financial Plan · Torque'!B42+'Monthly Financial Plan · Torque'!B43 -> 700 | C44: ='Monthly Financial Plan · Torque'!C41+'Monthly Financial Plan · Torque'!C42+'Monthly Financial Plan · Torque'!C43 -> 700 | D44: ='Monthly Financial Plan · Torque'!D41+'Monthly Financial Plan · Torque'!D42+'Monthly Financial Plan · Torque'!D43 -> 700 | E44: ='Monthly Financial Plan · Torque'!E41+'Monthly Financial Plan · Torque'!E42+'Monthly Financial Plan · Torque'!E43 -> 700 | F44: ='Monthly Financial Plan · Torque'!F41+'Monthly Financial Plan · Torque'!F42+'Monthly Financial Plan · Torque'!F43 -> 700 | G44: ='Monthly Financial Plan · Torque'!G41+'Monthly Financial Plan · Torque'!G42+'Monthly Financial Plan · Torque'!G43 -> 700 | H44: ='Monthly Financial Plan · Torque'!H41+'Monthly Financial Plan · Torque'!H42+'Monthly Financial Plan · Torque'!H43 -> 700 | I44: ='Monthly Financial Plan · Torque'!I41+'Monthly Financial Plan · Torque'!I42+'Monthly Financial Plan · Torque'!I43 -> 700 | ... M44: ='Monthly Financial Plan · Torque'!M41+'Monthly Financial Plan · Torque'!M42+'Monthly Financial Plan · Torque'!M43 -> 700
A45: Net cash flow before credits | B45: ='Monthly Financial Plan · Torque'!B35-'Monthly Financial Plan · Torque'!B44 -> -660.41676 | C45: ='Monthly Financial Plan · Torque'!C35-'Monthly Financial Plan · Torque'!C44 -> -431.64306 | D45: ='Monthly Financial Plan · Torque'!D35-'Monthly Financial Plan · Torque'!D44 -> -153.4717 | E45: ='Monthly Financial Plan · Torque'!E35-'Monthly Financial Plan · Torque'!E44 -> 186.83283 | F45: ='Monthly Financial Plan · Torque'!F35-'Monthly Financial Plan · Torque'!F44 -> 605.168 | G45: ='Monthly Financial Plan · Torque'!G35-'Monthly Financial Plan · Torque'!G44 -> 1121.3851 | H45: ='Monthly Financial Plan · Torque'!H35-'Monthly Financial Plan · Torque'!H44 -> 1760.2788 | I45: ='Monthly Financial Plan · Torque'!I35-'Monthly Financial Plan · Torque'!I44 -> 2552.8248 | ... M45: ='Monthly Financial Plan · Torque'!M35-'Monthly Financial Plan · Torque'!M44 -> 8193.5743
A46: Net cash flow after credits | B46: ='Monthly Financial Plan · Torque'!B39-'Monthly Financial Plan · Torque'!B44 -> -615.41676 | C46: ='Monthly Financial Plan · Torque'!C39-'Monthly Financial Plan · Torque'!C44 -> -431.64306 | D46: ='Monthly Financial Plan · Torque'!D39-'Monthly Financial Plan · Torque'!D44 -> -153.4717 | E46: ='Monthly Financial Plan · Torque'!E39-'Monthly Financial Plan · Torque'!E44 -> 186.83283 | F46: ='Monthly Financial Plan · Torque'!F39-'Monthly Financial Plan · Torque'!F44 -> 605.168 | G46: ='Monthly Financial Plan · Torque'!G39-'Monthly Financial Plan · Torque'!G44 -> 1121.3851 | H46: ='Monthly Financial Plan · Torque'!H39-'Monthly Financial Plan · Torque'!H44 -> 1760.2788 | I46: ='Monthly Financial Plan · Torque'!I39-'Monthly Financial Plan · Torque'!I44 -> 2552.8248 | ... M46: ='Monthly Financial Plan · Torque'!M39-'Monthly Financial Plan · Torque'!M44 -> 8193.5743
A47: Cash balance before credits | B47: ='Model inputs'!D12+'Monthly Financial Plan · Torque'!B45 -> -660.41676 | C47: ='Monthly Financial Plan · Torque'!B47+'Monthly Financial Plan · Torque'!C45 -> -1092.0598 | D47: ='Monthly Financial Plan · Torque'!C47+'Monthly Financial Plan · Torque'!D45 -> -1245.5315 | E47: ='Monthly Financial Plan · Torque'!D47+'Monthly Financial Plan · Torque'!E45 -> -1058.6987 | F47: ='Monthly Financial Plan · Torque'!E47+'Monthly Financial Plan · Torque'!F45 -> -453.53069 | G47: ='Monthly Financial Plan · Torque'!F47+'Monthly Financial Plan · Torque'!G45 -> 667.85438 | H47: ='Monthly Financial Plan · Torque'!G47+'Monthly Financial Plan · Torque'!H45 -> 2428.1332 | I47: ='Monthly Financial Plan · Torque'!H47+'Monthly Financial Plan · Torque'!I45 -> 4980.958 | J47: ='Monthly Financial Plan · Torque'!I47+'Monthly Financial Plan · Torque'!J45 -> 8518.6833 | ... M47: ='Monthly Financial Plan · Torque'!L47+'Monthly Financial Plan · Torque'!M45 -> 27765.715
A48: Cash balance after credits | B48: ='Model inputs'!D11+'Monthly Financial Plan · Torque'!B46 -> -615.41676 | C48: ='Monthly Financial Plan · Torque'!B48+'Monthly Financial Plan · Torque'!C46 -> -1047.0598 | D48: ='Monthly Financial Plan · Torque'!C48+'Monthly Financial Plan · Torque'!D46 -> -1200.5315 | E48: ='Monthly Financial Plan · Torque'!D48+'Monthly Financial Plan · Torque'!E46 -> -1013.6987 | F48: ='Monthly Financial Plan · Torque'!E48+'Monthly Financial Plan · Torque'!F46 -> -408.53069 | G48: ='Monthly Financial Plan · Torque'!F48+'Monthly Financial Plan · Torque'!G46 -> 712.85438 | H48: ='Monthly Financial Plan · Torque'!G48+'Monthly Financial Plan · Torque'!H46 -> 2473.1332 | I48: ='Monthly Financial Plan · Torque'!H48+'Monthly Financial Plan · Torque'!I46 -> 5025.958 | J48: ='Monthly Financial Plan · Torque'!I48+'Monthly Financial Plan · Torque'!J46 -> 8563.6833 | ... M48: ='Monthly Financial Plan · Torque'!L48+'Monthly Financial Plan · Torque'!M46 -> 27810.715
A49: Runway months before credits | B49: =IF(IF(IF(ISERROR('Monthly Financial Plan · Torque'!B45>=0),'Monthly Financial Plan · Torque'!B45>=0,IF('Monthly Financial Plan · Torque'!B45="","",'Monthly Financial Plan · Torque'!B45>=0))="",FALSE,IF(ISERROR('Monthly Financial Plan · Torque'!B45>=0),'Monthly Financial Plan · Torque'!B45>=0,IF('Monthly Financial Plan · Torque'!B45="","",'Monthly Financial Plan · Torque'!B45>=0))),"",IF(IF(IF(ISERROR('Monthly Financial Plan · Torque'!B47<=0),'Monthly Financial Plan · Torque'!B47<=0,IF('Monthly Financial Plan · Torque'!B47="","",'Monthly Financial Plan · Torque'!B47<=0))="",FALSE,IF(ISERROR('Monthly Financial Plan · Torque'!B47<=0),'Monthly Financial Plan · Torque'!B47<=0,IF('Monthly Financial Plan · Torque'!B47="","",'Monthly Financial Plan · Torque'!B47<=0))),0,'Monthly Financial Plan · Torque'!B47/(0-'Monthly Financial Plan · Torque'!B45))) -> 0 | C49: =IF(IF(IF(ISERROR('Monthly Financial Plan · Torque'!C45>=0),'Monthly Financial Plan · Torque'!C45>=0,IF('Monthly Financial Plan · Torque'!C45="","",'Monthly Financial Plan · Torque'!C45>=0))="",FALSE,IF(ISERROR('Monthly Financial Plan · Torque'!C45>=0),'Monthly Financial Plan · Torque'!C45>=0,IF('Monthly Financial Plan · Torque'!C45="","",'Monthly Financial Plan · Torque'!C45>=0))),"",IF(IF(IF(ISERROR('Monthly Financial Plan · Torque'!C47<=0),'Monthly Financial Plan · Torque'!C47<=0,IF('Monthly Financial Plan · Torque'!C47="","",'Monthly Financial Plan · Torque'!C47<=0))="",FALSE,IF(ISERROR('Monthly Financial Plan · Torque'!C47<=0),'Monthly Financial Plan · Torque'!C47<=0,IF('Monthly Financial Plan · Torque'!C47="","",'Monthly Financial Plan · Torque'!C47<=0))),0,'Monthly Financial Plan · Torque'!C47/(0-'Monthly Financial Plan · Torque'!C45))) -> 0 | D49: =IF(IF(IF(ISERROR('Monthly Financial Plan · Torque'!D45>=0),'Monthly Financial Plan · Torque'!D45>=0,IF('Monthly Financial Plan · Torque'!D45="","",'Monthly Financial Plan · Torque'!D45>=0))="",FALSE,IF(ISERROR('Monthly Financial Plan · Torque'!D45>=0),'Monthly Financial Plan · Torque'!D45>=0,IF('Monthly Financial Plan · Torque'!D45="","",'Monthly Financial Plan · Torque'!D45>=0))),"",IF(IF(IF(ISERROR('Monthly Financial Plan · Torque'!D47<=0),'Monthly Financial Plan · Torque'!D47<=0,IF('Monthly Financial Plan · Torque'!D47="","",'Monthly Financial Plan · Torque'!D47<=0))="",FALSE,IF(ISERROR('Monthly Financial Plan · Torque'!D47<=0),'Monthly Financial Plan · Torque'!D47<=0,IF('Monthly Financial Plan · Torque'!D47="","",'Monthly Financial Plan · Torque'!D47<=0))),0,'Monthly Financial Plan · Torque'!D47/(0-'Monthly Financial Plan · Torque'!D45))) -> 0 | E49: =IF(IF(IF(ISERROR('Monthly Financial Plan · Torque'!E45>=0),'Monthly Financial Plan · Torque'!E45>=0,IF('Monthly Financial Plan · Torque'!E45="","",'Monthly Financial Plan · Torque'!E45>=0))="",FALSE,IF(ISERROR('Monthly Financial Plan · Torque'!E45>=0),'Monthly Financial Plan · Torque'!E45>=0,IF('Monthly Financial Plan · Torque'!E45="","",'Monthly Financial Plan · Torque'!E45>=0))),"",IF(IF(IF(ISERROR('Monthly Financial Plan · Torque'!E47<=0),'Monthly Financial Plan · Torque'!E47<=0,IF('Monthly Financial Plan · Torque'!E47="","",'Monthly Financial Plan · Torque'!E47<=0))="",FALSE,IF(ISERROR('Monthly Financial Plan · Torque'!E47<=0),'Monthly Financial Plan · Torque'!E47<=0,IF('Monthly Financial Plan · Torque'!E47="","",'Monthly Financial Plan · Torque'!E47<=0))),0,'Monthly Financial Plan · Torque'!E47/(0-'Monthly Financial Plan · Torque'!E45))) | F49: =IF(IF(IF(ISERROR('Monthly Financial Plan · Torque'!F45>=0),'Monthly Financial Plan · Torque'!F45>=0,IF('Monthly Financial Plan · Torque'!F45="","",'Monthly Financial Plan · Torque'!F45>=0))="",FALSE,IF(ISERROR('Monthly Financial Plan · Torque'!F45>=0),'Monthly Financial Plan · Torque'!F45>=0,IF('Monthly Financial Plan · Torque'!F45="","",'Monthly Financial Plan · Torque'!F45>=0))),"",IF(IF(IF(ISERROR('Monthly Financial Plan · Torque'!F47<=0),'Monthly Financial Plan · Torque'!F47<=0,IF('Monthly Financial Plan · Torque'!F47="","",'Monthly Financial Plan · Torque'!F47<=0))="",FALSE,IF(ISERROR('Monthly Financial Plan · Torque'!F47<=0),'Monthly Financial Plan · Torque'!F47<=0,IF('Monthly Financial Plan · Torque'!F47="","",'Monthly Financial Plan · Torque'!F47<=0))),0,'Monthly Financial Plan · Torque'!F47/(0-'Monthly Financial Plan · Torque'!F45))) | G49: =IF(IF(IF(ISERROR('Monthly Financial Plan · Torque'!G45>=0),'Monthly Financial Plan · Torque'!G45>=0,IF('Monthly Financial Plan · Torque'!G45="","",'Monthly Financial Plan · Torque'!G45>=0))="",FALSE,IF(ISERROR('Monthly Financial Plan · Torque'!G45>=0),'Monthly Financial Plan · Torque'!G45>=0,IF('Monthly Financial Plan · Torque'!G45="","",'Monthly Financial Plan · Torque'!G45>=0))),"",IF(IF(IF(ISERROR('Monthly Financial Plan · Torque'!G47<=0),'Monthly Financial Plan · Torque'!G47<=0,IF('Monthly Financial Plan · Torque'!G47="","",'Monthly Financial Plan · Torque'!G47<=0))="",FALSE,IF(ISERROR('Monthly Financial Plan · Torque'!G47<=0),'Monthly Financial Plan · Torque'!G47<=0,IF('Monthly Financial Plan · Torque'!G47="","",'Monthly Financial Plan · Torque'!G47<=0))),0,'Monthly Financial Plan · Torque'!G47/(0-'Monthly Financial Plan · Torque'!G45))) | H49: =IF(IF(IF(ISERROR('Monthly Financial Plan · Torque'!H45>=0),'Monthly Financial Plan · Torque'!H45>=0,IF('Monthly Financial Plan · Torque'!H45="","",'Monthly Financial Plan · Torque'!H45>=0))="",FALSE,IF(ISERROR('Monthly Financial Plan · Torque'!H45>=0),'Monthly Financial Plan · Torque'!H45>=0,IF('Monthly Financial Plan · Torque'!H45="","",'Monthly Financial Plan · Torque'!H45>=0))),"",IF(IF(IF(ISERROR('Monthly Financial Plan · Torque'!H47<=0),'Monthly Financial Plan · Torque'!H47<=0,IF('Monthly Financial Plan · Torque'!H47="","",'Monthly Financial Plan · Torque'!H47<=0))="",FALSE,IF(ISERROR('Monthly Financial Plan · Torque'!H47<=0),'Monthly Financial Plan · Torque'!H47<=0,IF('Monthly Financial Plan · Torque'!H47="","",'Monthly Financial Plan · Torque'!H47<=0))),0,'Monthly Financial Plan · Torque'!H47/(0-'Monthly Financial Plan · Torque'!H45))) | I49: =IF(IF(IF(ISERROR('Monthly Financial Plan · Torque'!I45>=0),'Monthly Financial Plan · Torque'!I45>=0,IF('Monthly Financial Plan · Torque'!I45="","",'Monthly Financial Plan · Torque'!I45>=0))="",FALSE,IF(ISERROR('Monthly Financial Plan · Torque'!I45>=0),'Monthly Financial Plan · Torque'!I45>=0,IF('Monthly Financial Plan · Torque'!I45="","",'Monthly Financial Plan · Torque'!I45>=0))),"",IF(IF(IF(ISERROR('Monthly Financial Plan · Torque'!I47<=0),'Monthly Financial Plan · Torque'!I47<=0,IF('Monthly Financial Plan · Torque'!I47="","",'Monthly Financial Plan · Torque'!I47<=0))="",FALSE,IF(ISERROR('Monthly Financial Plan · Torque'!I47<=0),'Monthly Financial Plan · Torque'!I47<=0,IF('Monthly Financial Plan · Torque'!I47="","",'Monthly Financial Plan · Torque'!I47<=0))),0,'Monthly Financial Plan · Torque'!I47/(0-'Monthly Financial Plan · Torque'!I45))) | ... M49: =IF(IF(IF(ISERROR('Monthly Financial Plan · Torque'!M45>=0),'Monthly Financial Plan · Torque'!M45>=0,IF('Monthly Financial Plan · Torque'!M45="","",'Monthly Financial Plan · Torque'!M45>=0))="",FALSE,IF(ISERROR('Monthly Financial Plan · Torque'!M45>=0),'Monthly Financial Plan · Torque'!M45>=0,IF('Monthly Financial Plan · Torque'!M45="","",'Monthly Financial Plan · Torque'!M45>=0))),"",IF(IF(IF(ISERROR('Monthly Financial Plan · Torque'!M47<=0),'Monthly Financial Plan · Torque'!M47<=0,IF('Monthly Financial Plan · Torque'!M47="","",'Monthly Financial Plan · Torque'!M47<=0))="",FALSE,IF(ISERROR('Monthly Financial Plan · Torque'!M47<=0),'Monthly Financial Plan · Torque'!M47<=0,IF('Monthly Financial Plan · Torque'!M47="","",'Monthly Financial Plan · Torque'!M47<=0))),0,'Monthly Financial Plan · Torque'!M47/(0-'Monthly Financial Plan · Torque'!M45)))
A50: Runway months after credits | B50: =IF(IF(IF(ISERROR('Monthly Financial Plan · Torque'!B46>=0),'Monthly Financial Plan · Torque'!B46>=0,IF('Monthly Financial Plan · Torque'!B46="","",'Monthly Financial Plan · Torque'!B46>=0))="",FALSE,IF(ISERROR('Monthly Financial Plan · Torque'!B46>=0),'Monthly Financial Plan · Torque'!B46>=0,IF('Monthly Financial Plan · Torque'!B46="","",'Monthly Financial Plan · Torque'!B46>=0))),"",IF(IF(IF(ISERROR('Monthly Financial Plan · Torque'!B48<=0),'Monthly Financial Plan · Torque'!B48<=0,IF('Monthly Financial Plan · Torque'!B48="","",'Monthly Financial Plan · Torque'!B48<=0))="",FALSE,IF(ISERROR('Monthly Financial Plan · Torque'!B48<=0),'Monthly Financial Plan · Torque'!B48<=0,IF('Monthly Financial Plan · Torque'!B48="","",'Monthly Financial Plan · Torque'!B48<=0))),0,'Monthly Financial Plan · Torque'!B48/(0-'Monthly Financial Plan · Torque'!B46))) -> 0 | C50: =IF(IF(IF(ISERROR('Monthly Financial Plan · Torque'!C46>=0),'Monthly Financial Plan · Torque'!C46>=0,IF('Monthly Financial Plan · Torque'!C46="","",'Monthly Financial Plan · Torque'!C46>=0))="",FALSE,IF(ISERROR('Monthly Financial Plan · Torque'!C46>=0),'Monthly Financial Plan · Torque'!C46>=0,IF('Monthly Financial Plan · Torque'!C46="","",'Monthly Financial Plan · Torque'!C46>=0))),"",IF(IF(IF(ISERROR('Monthly Financial Plan · Torque'!C48<=0),'Monthly Financial Plan · Torque'!C48<=0,IF('Monthly Financial Plan · Torque'!C48="","",'Monthly Financial Plan · Torque'!C48<=0))="",FALSE,IF(ISERROR('Monthly Financial Plan · Torque'!C48<=0),'Monthly Financial Plan · Torque'!C48<=0,IF('Monthly Financial Plan · Torque'!C48="","",'Monthly Financial Plan · Torque'!C48<=0))),0,'Monthly Financial Plan · Torque'!C48/(0-'Monthly Financial Plan · Torque'!C46))) -> 0 | D50: =IF(IF(IF(ISERROR('Monthly Financial Plan · Torque'!D46>=0),'Monthly Financial Plan · Torque'!D46>=0,IF('Monthly Financial Plan · Torque'!D46="","",'Monthly Financial Plan · Torque'!D46>=0))="",FALSE,IF(ISERROR('Monthly Financial Plan · Torque'!D46>=0),'Monthly Financial Plan · Torque'!D46>=0,IF('Monthly Financial Plan · Torque'!D46="","",'Monthly Financial Plan · Torque'!D46>=0))),"",IF(IF(IF(ISERROR('Monthly Financial Plan · Torque'!D48<=0),'Monthly Financial Plan · Torque'!D48<=0,IF('Monthly Financial Plan · Torque'!D48="","",'Monthly Financial Plan · Torque'!D48<=0))="",FALSE,IF(ISERROR('Monthly Financial Plan · Torque'!D48<=0),'Monthly Financial Plan · Torque'!D48<=0,IF('Monthly Financial Plan · Torque'!D48="","",'Monthly Financial Plan · Torque'!D48<=0))),0,'Monthly Financial Plan · Torque'!D48/(0-'Monthly Financial Plan · Torque'!D46))) -> 0 | E50: =IF(IF(IF(ISERROR('Monthly Financial Plan · Torque'!E46>=0),'Monthly Financial Plan · Torque'!E46>=0,IF('Monthly Financial Plan · Torque'!E46="","",'Monthly Financial Plan · Torque'!E46>=0))="",FALSE,IF(ISERROR('Monthly Financial Plan · Torque'!E46>=0),'Monthly Financial Plan · Torque'!E46>=0,IF('Monthly Financial Plan · Torque'!E46="","",'Monthly Financial Plan · Torque'!E46>=0))),"",IF(IF(IF(ISERROR('Monthly Financial Plan · Torque'!E48<=0),'Monthly Financial Plan · Torque'!E48<=0,IF('Monthly Financial Plan · Torque'!E48="","",'Monthly Financial Plan · Torque'!E48<=0))="",FALSE,IF(ISERROR('Monthly Financial Plan · Torque'!E48<=0),'Monthly Financial Plan · Torque'!E48<=0,IF('Monthly Financial Plan · Torque'!E48="","",'Monthly Financial Plan · Torque'!E48<=0))),0,'Monthly Financial Plan · Torque'!E48/(0-'Monthly Financial Plan · Torque'!E46))) | F50: =IF(IF(IF(ISERROR('Monthly Financial Plan · Torque'!F46>=0),'Monthly Financial Plan · Torque'!F46>=0,IF('Monthly Financial Plan · Torque'!F46="","",'Monthly Financial Plan · Torque'!F46>=0))="",FALSE,IF(ISERROR('Monthly Financial Plan · Torque'!F46>=0),'Monthly Financial Plan · Torque'!F46>=0,IF('Monthly Financial Plan · Torque'!F46="","",'Monthly Financial Plan · Torque'!F46>=0))),"",IF(IF(IF(ISERROR('Monthly Financial Plan · Torque'!F48<=0),'Monthly Financial Plan · Torque'!F48<=0,IF('Monthly Financial Plan · Torque'!F48="","",'Monthly Financial Plan · Torque'!F48<=0))="",FALSE,IF(ISERROR('Monthly Financial Plan · Torque'!F48<=0),'Monthly Financial Plan · Torque'!F48<=0,IF('Monthly Financial Plan · Torque'!F48="","",'Monthly Financial Plan · Torque'!F48<=0))),0,'Monthly Financial Plan · Torque'!F48/(0-'Monthly Financial Plan · Torque'!F46))) | G50: =IF(IF(IF(ISERROR('Monthly Financial Plan · Torque'!G46>=0),'Monthly Financial Plan · Torque'!G46>=0,IF('Monthly Financial Plan · Torque'!G46="","",'Monthly Financial Plan · Torque'!G46>=0))="",FALSE,IF(ISERROR('Monthly Financial Plan · Torque'!G46>=0),'Monthly Financial Plan · Torque'!G46>=0,IF('Monthly Financial Plan · Torque'!G46="","",'Monthly Financial Plan · Torque'!G46>=0))),"",IF(IF(IF(ISERROR('Monthly Financial Plan · Torque'!G48<=0),'Monthly Financial Plan · Torque'!G48<=0,IF('Monthly Financial Plan · Torque'!G48="","",'Monthly Financial Plan · Torque'!G48<=0))="",FALSE,IF(ISERROR('Monthly Financial Plan · Torque'!G48<=0),'Monthly Financial Plan · Torque'!G48<=0,IF('Monthly Financial Plan · Torque'!G48="","",'Monthly Financial Plan · Torque'!G48<=0))),0,'Monthly Financial Plan · Torque'!G48/(0-'Monthly Financial Plan · Torque'!G46))) | H50: =IF(IF(IF(ISERROR('Monthly Financial Plan · Torque'!H46>=0),'Monthly Financial Plan · Torque'!H46>=0,IF('Monthly Financial Plan · Torque'!H46="","",'Monthly Financial Plan · Torque'!H46>=0))="",FALSE,IF(ISERROR('Monthly Financial Plan · Torque'!H46>=0),'Monthly Financial Plan · Torque'!H46>=0,IF('Monthly Financial Plan · Torque'!H46="","",'Monthly Financial Plan · Torque'!H46>=0))),"",IF(IF(IF(ISERROR('Monthly Financial Plan · Torque'!H48<=0),'Monthly Financial Plan · Torque'!H48<=0,IF('Monthly Financial Plan · Torque'!H48="","",'Monthly Financial Plan · Torque'!H48<=0))="",FALSE,IF(ISERROR('Monthly Financial Plan · Torque'!H48<=0),'Monthly Financial Plan · Torque'!H48<=0,IF('Monthly Financial Plan · Torque'!H48="","",'Monthly Financial Plan · Torque'!H48<=0))),0,'Monthly Financial Plan · Torque'!H48/(0-'Monthly Financial Plan · Torque'!H46))) | I50: =IF(IF(IF(ISERROR('Monthly Financial Plan · Torque'!I46>=0),'Monthly Financial Plan · Torque'!I46>=0,IF('Monthly Financial Plan · Torque'!I46="","",'Monthly Financial Plan · Torque'!I46>=0))="",FALSE,IF(ISERROR('Monthly Financial Plan · Torque'!I46>=0),'Monthly Financial Plan · Torque'!I46>=0,IF('Monthly Financial Plan · Torque'!I46="","",'Monthly Financial Plan · Torque'!I46>=0))),"",IF(IF(IF(ISERROR('Monthly Financial Plan · Torque'!I48<=0),'Monthly Financial Plan · Torque'!I48<=0,IF('Monthly Financial Plan · Torque'!I48="","",'Monthly Financial Plan · Torque'!I48<=0))="",FALSE,IF(ISERROR('Monthly Financial Plan · Torque'!I48<=0),'Monthly Financial Plan · Torque'!I48<=0,IF('Monthly Financial Plan · Torque'!I48="","",'Monthly Financial Plan · Torque'!I48<=0))),0,'Monthly Financial Plan · Torque'!I48/(0-'Monthly Financial Plan · Torque'!I46))) | ... M50: =IF(IF(IF(ISERROR('Monthly Financial Plan · Torque'!M46>=0),'Monthly Financial Plan · Torque'!M46>=0,IF('Monthly Financial Plan · Torque'!M46="","",'Monthly Financial Plan · Torque'!M46>=0))="",FALSE,IF(ISERROR('Monthly Financial Plan · Torque'!M46>=0),'Monthly Financial Plan · Torque'!M46>=0,IF('Monthly Financial Plan · Torque'!M46="","",'Monthly Financial Plan · Torque'!M46>=0))),"",IF(IF(IF(ISERROR('Monthly Financial Plan · Torque'!M48<=0),'Monthly Financial Plan · Torque'!M48<=0,IF('Monthly Financial Plan · Torque'!M48="","",'Monthly Financial Plan · Torque'!M48<=0))="",FALSE,IF(ISERROR('Monthly Financial Plan · Torque'!M48<=0),'Monthly Financial Plan · Torque'!M48<=0,IF('Monthly Financial Plan · Torque'!M48="","",'Monthly Financial Plan · Torque'!M48<=0))),0,'Monthly Financial Plan · Torque'!M48/(0-'Monthly Financial Plan · Torque'!M46)))
A51: AI spend limit at target margin | B51: ='Monthly Financial Plan · Torque'!B27*(1-'Torque Assumptions · Growth & o'!B12)-'Monthly Financial Plan · Torque'!B32-'Monthly Financial Plan · Torque'!B33-'Monthly Financial Plan · Torque'!B30-'Monthly Financial Plan · Torque'!B31 -> -42.174413 | C51: ='Monthly Financial Plan · Torque'!C27*(1-'Torque Assumptions · Growth & o'!B12)-'Monthly Financial Plan · Torque'!C32-'Monthly Financial Plan · Torque'!C33-'Monthly Financial Plan · Torque'!C30-'Monthly Financial Plan · Torque'!C31 -> 88.002512 | D51: ='Monthly Financial Plan · Torque'!D27*(1-'Torque Assumptions · Growth & o'!B12)-'Monthly Financial Plan · Torque'!D32-'Monthly Financial Plan · Torque'!D33-'Monthly Financial Plan · Torque'!D30-'Monthly Financial Plan · Torque'!D31 -> 246.3458 | E51: ='Monthly Financial Plan · Torque'!E27*(1-'Torque Assumptions · Growth & o'!B12)-'Monthly Financial Plan · Torque'!E32-'Monthly Financial Plan · Torque'!E33-'Monthly Financial Plan · Torque'!E30-'Monthly Financial Plan · Torque'!E31 -> 440.11133 | F51: ='Monthly Financial Plan · Torque'!F27*(1-'Torque Assumptions · Growth & o'!B12)-'Monthly Financial Plan · Torque'!F32-'Monthly Financial Plan · Torque'!F33-'Monthly Financial Plan · Torque'!F30-'Monthly Financial Plan · Torque'!F31 -> 678.35685 | G51: ='Monthly Financial Plan · Torque'!G27*(1-'Torque Assumptions · Growth & o'!B12)-'Monthly Financial Plan · Torque'!G32-'Monthly Financial Plan · Torque'!G33-'Monthly Financial Plan · Torque'!G30-'Monthly Financial Plan · Torque'!G31 -> 972.39324 | H51: ='Monthly Financial Plan · Torque'!H27*(1-'Torque Assumptions · Growth & o'!B12)-'Monthly Financial Plan · Torque'!H32-'Monthly Financial Plan · Torque'!H33-'Monthly Financial Plan · Torque'!H30-'Monthly Financial Plan · Torque'!H31 -> 1336.3485 | I51: ='Monthly Financial Plan · Torque'!I27*(1-'Torque Assumptions · Growth & o'!B12)-'Monthly Financial Plan · Torque'!I32-'Monthly Financial Plan · Torque'!I33-'Monthly Financial Plan · Torque'!I30-'Monthly Financial Plan · Torque'!I31 -> 1787.8726 | J51: ='Monthly Financial Plan · Torque'!J27*(1-'Torque Assumptions · Growth & o'!B12)-'Monthly Financial Plan · Torque'!J32-'Monthly Financial Plan · Torque'!J33-'Monthly Financial Plan · Torque'!J30-'Monthly Financial Plan · Torque'!J31 -> 2349.0189 | K51: ='Monthly Financial Plan · Torque'!K27*(1-'Torque Assumptions · Growth & o'!B12)-'Monthly Financial Plan · Torque'!K32-'Monthly Financial Plan · Torque'!K33-'Monthly Financial Plan · Torque'!K30-'Monthly Financial Plan · Torque'!K31 -> 3047.345 | L51: ='Monthly Financial Plan · Torque'!L27*(1-'Torque Assumptions · Growth & o'!B12)-'Monthly Financial Plan · Torque'!L32-'Monthly Financial Plan · Torque'!L33-'Monthly Financial Plan · Torque'!L30-'Monthly Financial Plan · Torque'!L31 -> 3917.2901 | M51: ='Monthly Financial Plan · Torque'!M27*(1-'Torque Assumptions · Growth & o'!B12)-'Monthly Financial Plan · Torque'!M32-'Monthly Financial Plan · Torque'!M33-'Monthly Financial Plan · Torque'!M30-'Monthly Financial Plan · Torque'!M31 -> 5001.8953

Sheet Unit Economics & Sensitivity ·
A1: Unit Economics & Sensitivity · Unit economics per issue run
A2: Financial model (4 pages) · Main Scenario
A4: Variable / dimension | B4: Value
A5: LLM cost per attempt | B5: =('Torque Assumptions · Run cost a'!B5*'Torque Assumptions · Run cost a'!B7+'Torque Assumptions · Run cost a'!B6*'Torque Assumptions · Run cost a'!B8)/1000000 -> 0.75
A6: Sandbox cost per attempt | B6: ='Torque Assumptions · Run cost a'!B12*'Torque Assumptions · Run cost a'!B13 -> 0.06
A7: Attempt equivalents per run | B7: =1+MIN('Torque Assumptions · Run cost a'!B9,'Torque Assumptions · Run cost a'!B10)*'Torque Assumptions · Run cost a'!B11 -> 1.3
A8: LLM cost per run | B8: ='Unit Economics & Sensitivity ·'!B5*'Unit Economics & Sensitivity ·'!B7 -> 0.975
A9: Sandbox cost per run | B9: ='Unit Economics & Sensitivity ·'!B6*'Unit Economics & Sensitivity ·'!B7 -> 0.078
A10: Tooling and storage cost per run | B10: ='Torque Assumptions · Run cost a'!B14+'Torque Assumptions · Run cost a'!B15+'Torque Assumptions · Run cost a'!B16 -> 0.025
A11: Cost per attempted issue run | B11: ='Unit Economics & Sensitivity ·'!B8+'Unit Economics & Sensitivity ·'!B9+'Unit Economics & Sensitivity ·'!B10 -> 1.078
A12: Cost per verified pull request | B12: =IFERROR('Unit Economics & Sensitivity ·'!B11/'Torque Assumptions · Run cost a'!B17,"") -> 1.7966667
A13: Worst case cost per run at retry limit | B13: =('Unit Economics & Sensitivity ·'!B5+'Unit Economics & Sensitivity ·'!B6)*(1+'Torque Assumptions · Run cost a'!B10*'Torque Assumptions · Run cost a'!B11)+'Unit Economics & Sensitivity ·'!B10 -> 1.645
A14: Blended revenue per customer | B14: =SUM('Torque Assumptions · Tier prici'!L5,'Torque Assumptions · Tier prici'!L6,'Torque Assumptions · Tier prici'!L7) -> 116.4875
A15: Blended runs per customer | B15: =SUM('Torque Assumptions · Tier prici'!M5,'Torque Assumptions · Tier prici'!M6,'Torque Assumptions · Tier prici'!M7) -> 46.025
A16: Blended full allowance runs per customer | B16: =SUM('Torque Assumptions · Tier prici'!N5,'Torque Assumptions · Tier prici'!N6,'Torque Assumptions · Tier prici'!N7) -> 72.05
A17: Variable cost per customer | B17: ='Unit Economics & Sensitivity ·'!B15*'Unit Economics & Sensitivity ·'!B11+'Unit Economics & Sensitivity ·'!B14*'Torque Assumptions · Growth & o'!B13+'Torque Assumptions · Growth & o'!B14 -> 53.293087
A18: Contribution per customer | B18: ='Unit Economics & Sensitivity ·'!B14-'Unit Economics & Sensitivity ·'!B17 -> 63.194412
A19: Contribution margin | B19: =IFERROR('Unit Economics & Sensitivity ·'!B18/'Unit Economics & Sensitivity ·'!B14,"") -> 0.54249952
A20: Fixed monthly costs | B20: ='Torque Assumptions · Growth & o'!B7+'Torque Assumptions · Growth & o'!B8+'Torque Assumptions · Growth & o'!B9+'Torque Assumptions · Growth & o'!B10 -> 850
A21: Break even customers | B21: =IF(IF(IF(ISERROR('Unit Economics & Sensitivity ·'!B18>0),'Unit Economics & Sensitivity ·'!B18>0,IF('Unit Economics & Sensitivity ·'!B18="","",'Unit Economics & Sensitivity ·'!B18>0))="",FALSE,IF(ISERROR('Unit Economics & Sensitivity ·'!B18>0),'Unit Economics & Sensitivity ·'!B18>0,IF('Unit Economics & Sensitivity ·'!B18="","",'Unit Economics & Sensitivity ·'!B18>0))),CEILING('Unit Economics & Sensitivity ·'!B20/'Unit Economics & Sensitivity ·'!B18,1),"") -> 14
A22: Max run spend per customer at target margin | B22: ='Unit Economics & Sensitivity ·'!B14*(1-'Torque Assumptions · Growth & o'!B12)-'Unit Economics & Sensitivity ·'!B14*'Torque Assumptions · Growth & o'!B13-'Torque Assumptions · Growth & o'!B14 -> 37.092487
A23: Max runs per customer at target margin | B23: =IFERROR('Unit Economics & Sensitivity ·'!B22/'Unit Economics & Sensitivity ·'!B11,"") -> 34.408615

Sheet Unit Economics & Sensitivit (2)
A1: Unit Economics & Sensitivity · Sensitivity: cost and margin stress tests
A2: Financial model (4 pages) · Main Scenario
A4: Variable / dimension | B4: Model cost multiplier | C4: Retry multiplier | D4: Success rate change | E4: Full allowance flag | F4: Stressed cost per run | G4: Stressed success rate | H4: Stressed cost per verified PR | I4: Stressed runs per customer | J4: Stressed contribution per customer | K4: Stressed contribution margin | L4: Stressed break even customers
A5: Base case | B5: =1 -> 1 | C5: =1 -> 1 | D5: =0 -> 0 | E5: =0 -> 0 | F5: =('Unit Economics & Sensitivity ·'!B5*'Unit Economics & Sensitivit (2)'!B5+'Unit Economics & Sensitivity ·'!B6)*(1+MIN('Torque Assumptions · Run cost a'!B9*'Unit Economics & Sensitivit (2)'!C5,'Torque Assumptions · Run cost a'!B10)*'Torque Assumptions · Run cost a'!B11)+'Unit Economics & Sensitivity ·'!B10 -> 1.078 | G5: ='Torque Assumptions · Run cost a'!B17+'Unit Economics & Sensitivit (2)'!D5 -> 0.6 | H5: =IFERROR('Unit Economics & Sensitivit (2)'!F5/'Unit Economics & Sensitivit (2)'!G5,"") -> 1.7966667 | I5: =IF(IF(IF(ISERROR('Unit Economics & Sensitivit (2)'!E5=1),'Unit Economics & Sensitivit (2)'!E5=1,IF('Unit Economics & Sensitivit (2)'!E5="","",'Unit Economics & Sensitivit (2)'!E5=1))="",FALSE,IF(ISERROR('Unit Economics & Sensitivit (2)'!E5=1),'Unit Economics & Sensitivit (2)'!E5=1,IF('Unit Economics & Sensitivit (2)'!E5="","",'Unit Economics & Sensitivit (2)'!E5=1))),IF('Unit Economics & Sensitivity ·'!B16="","",'Unit Economics & Sensitivity ·'!B16),IF('Unit Economics & Sensitivity ·'!B15="","",'Unit Economics & Sensitivity ·'!B15)) -> 46.025 | J5: ='Unit Economics & Sensitivity ·'!B14-'Unit Economics & Sensitivit (2)'!I5*'Unit Economics & Sensitivit (2)'!F5-'Unit Economics & Sensitivity ·'!B14*'Torque Assumptions · Growth & o'!B13-'Torque Assumptions · Growth & o'!B14 -> 63.194412 | K5: =IFERROR('Unit Economics & Sensitivit (2)'!J5/'Unit Economics & Sensitivity ·'!B14,"") -> 0.54249952 | L5: =IF(IF(IF(ISERROR('Unit Economics & Sensitivit (2)'!J5>0),'Unit Economics & Sensitivit (2)'!J5>0,IF('Unit Economics & Sensitivit (2)'!J5="","",'Unit Economics & Sensitivit (2)'!J5>0))="",FALSE,IF(ISERROR('Unit Economics & Sensitivit (2)'!J5>0),'Unit Economics & Sensitivit (2)'!J5>0,IF('Unit Economics & Sensitivit (2)'!J5="","",'Unit Economics & Sensitivit (2)'!J5>0))),CEILING('Unit Economics & Sensitivity ·'!B20/'Unit Economics & Sensitivit (2)'!J5,1),"") -> 14
A6: Model costs +50% | B6: =1.5 -> 1.5 | C6: =1 -> 1 | D6: =0 -> 0 | E6: =0 -> 0 | F6: =('Unit Economics & Sensitivity ·'!B5*'Unit Economics & Sensitivit (2)'!B6+'Unit Economics & Sensitivity ·'!B6)*(1+MIN('Torque Assumptions · Run cost a'!B9*'Unit Economics & Sensitivit (2)'!C6,'Torque Assumptions · Run cost a'!B10)*'Torque Assumptions · Run cost a'!B11)+'Unit Economics & Sensitivity ·'!B10 -> 1.5655 | G6: ='Torque Assumptions · Run cost a'!B17+'Unit Economics & Sensitivit (2)'!D6 -> 0.6 | H6: =IFERROR('Unit Economics & Sensitivit (2)'!F6/'Unit Economics & Sensitivit (2)'!G6,"") -> 2.6091667 | I6: =IF(IF(IF(ISERROR('Unit Economics & Sensitivit (2)'!E6=1),'Unit Economics & Sensitivit (2)'!E6=1,IF('Unit Economics & Sensitivit (2)'!E6="","",'Unit Economics & Sensitivit (2)'!E6=1))="",FALSE,IF(ISERROR('Unit Economics & Sensitivit (2)'!E6=1),'Unit Economics & Sensitivit (2)'!E6=1,IF('Unit Economics & Sensitivit (2)'!E6="","",'Unit Economics & Sensitivit (2)'!E6=1))),IF('Unit Economics & Sensitivity ·'!B16="","",'Unit Economics & Sensitivity ·'!B16),IF('Unit Economics & Sensitivity ·'!B15="","",'Unit Economics & Sensitivity ·'!B15)) -> 46.025 | J6: ='Unit Economics & Sensitivity ·'!B14-'Unit Economics & Sensitivit (2)'!I6*'Unit Economics & Sensitivit (2)'!F6-'Unit Economics & Sensitivity ·'!B14*'Torque Assumptions · Growth & o'!B13-'Torque Assumptions · Growth & o'!B14 -> 40.757225 | K6: =IFERROR('Unit Economics & Sensitivit (2)'!J6/'Unit Economics & Sensitivity ·'!B14,"") -> 0.34988497 | L6: =IF(IF(IF(ISERROR('Unit Economics & Sensitivit (2)'!J6>0),'Unit Economics & Sensitivit (2)'!J6>0,IF('Unit Economics & Sensitivit (2)'!J6="","",'Unit Economics & Sensitivit (2)'!J6>0))="",FALSE,IF(ISERROR('Unit Economics & Sensitivit (2)'!J6>0),'Unit Economics & Sensitivit (2)'!J6>0,IF('Unit Economics & Sensitivit (2)'!J6="","",'Unit Economics & Sensitivit (2)'!J6>0))),CEILING('Unit Economics & Sensitivity ·'!B20/'Unit Economics & Sensitivit (2)'!J6,1),"") -> 21
A7: Retries doubled | B7: =1 -> 1 | C7: =2 -> 2 | D7: =0 -> 0 | E7: =0 -> 0 | F7: =('Unit Economics & Sensitivity ·'!B5*'Unit Economics & Sensitivit (2)'!B7+'Unit Economics & Sensitivity ·'!B6)*(1+MIN('Torque Assumptions · Run cost a'!B9*'Unit Economics & Sensitivit (2)'!C7,'Torque Assumptions · Run cost a'!B10)*'Torque Assumptions · Run cost a'!B11)+'Unit Economics & Sensitivity ·'!B10 -> 1.321 | G7: ='Torque Assumptions · Run cost a'!B17+'Unit Economics & Sensitivit (2)'!D7 -> 0.6 | H7: =IFERROR('Unit Economics & Sensitivit (2)'!F7/'Unit Economics & Sensitivit (2)'!G7,"") -> 2.2016667 | I7: =IF(IF(IF(ISERROR('Unit Economics & Sensitivit (2)'!E7=1),'Unit Economics & Sensitivit (2)'!E7=1,IF('Unit Economics & Sensitivit (2)'!E7="","",'Unit Economics & Sensitivit (2)'!E7=1))="",FALSE,IF(ISERROR('Unit Economics & Sensitivit (2)'!E7=1),'Unit Economics & Sensitivit (2)'!E7=1,IF('Unit Economics & Sensitivit (2)'!E7="","",'Unit Economics & Sensitivit (2)'!E7=1))),IF('Unit Economics & Sensitivity ·'!B16="","",'Unit Economics & Sensitivity ·'!B16),IF('Unit Economics & Sensitivity ·'!B15="","",'Unit Economics & Sensitivity ·'!B15)) -> 46.025 | J7: ='Unit Economics & Sensitivity ·'!B14-'Unit Economics & Sensitivit (2)'!I7*'Unit Economics & Sensitivit (2)'!F7-'Unit Economics & Sensitivity ·'!B14*'Torque Assumptions · Growth & o'!B13-'Torque Assumptions · Growth & o'!B14 -> 52.010337 | K7: =IFERROR('Unit Economics & Sensitivit (2)'!J7/'Unit Economics & Sensitivity ·'!B14,"") -> 0.44648857 | L7: =IF(IF(IF(ISERROR('Unit Economics & Sensitivit (2)'!J7>0),'Unit Economics & Sensitivit (2)'!J7>0,IF('Unit Economics & Sensitivit (2)'!J7="","",'Unit Economics & Sensitivit (2)'!J7>0))="",FALSE,IF(ISERROR('Unit Economics & Sensitivit (2)'!J7>0),'Unit Economics & Sensitivit (2)'!J7>0,IF('Unit Economics & Sensitivit (2)'!J7="","",'Unit Economics & Sensitivit (2)'!J7>0))),CEILING('Unit Economics & Sensitivity ·'!B20/'Unit Economics & Sensitivit (2)'!J7,1),"") -> 17
A8: Success rate -15 pts | B8: =1 -> 1 | C8: =1 -> 1 | D8: =-0.15 -> -0.15 | E8: =0 -> 0 | F8: =('Unit Economics & Sensitivity ·'!B5*'Unit Economics & Sensitivit (2)'!B8+'Unit Economics & Sensitivity ·'!B6)*(1+MIN('Torque Assumptions · Run cost a'!B9*'Unit Economics & Sensitivit (2)'!C8,'Torque Assumptions · Run cost a'!B10)*'Torque Assumptions · Run cost a'!B11)+'Unit Economics & Sensitivity ·'!B10 -> 1.078 | G8: ='Torque Assumptions · Run cost a'!B17+'Unit Economics & Sensitivit (2)'!D8 -> 0.45 | H8: =IFERROR('Unit Economics & Sensitivit (2)'!F8/'Unit Economics & Sensitivit (2)'!G8,"") -> 2.3955556 | I8: =IF(IF(IF(ISERROR('Unit Economics & Sensitivit (2)'!E8=1),'Unit Economics & Sensitivit (2)'!E8=1,IF('Unit Economics & Sensitivit (2)'!E8="","",'Unit Economics & Sensitivit (2)'!E8=1))="",FALSE,IF(ISERROR('Unit Economics & Sensitivit (2)'!E8=1),'Unit Economics & Sensitivit (2)'!E8=1,IF('Unit Economics & Sensitivit (2)'!E8="","",'Unit Economics & Sensitivit (2)'!E8=1))),IF('Unit Economics & Sensitivity ·'!B16="","",'Unit Economics & Sensitivity ·'!B16),IF('Unit Economics & Sensitivity ·'!B15="","",'Unit Economics & Sensitivity ·'!B15)) -> 46.025 | J8: ='Unit Economics & Sensitivity ·'!B14-'Unit Economics & Sensitivit (2)'!I8*'Unit Economics & Sensitivit (2)'!F8-'Unit Economics & Sensitivity ·'!B14*'Torque Assumptions · Growth & o'!B13-'Torque Assumptions · Growth & o'!B14 -> 63.194412 | K8: =IFERROR('Unit Economics & Sensitivit (2)'!J8/'Unit Economics & Sensitivity ·'!B14,"") -> 0.54249952 | L8: =IF(IF(IF(ISERROR('Unit Economics & Sensitivit (2)'!J8>0),'Unit Economics & Sensitivit (2)'!J8>0,IF('Unit Economics & Sensitivit (2)'!J8="","",'Unit Economics & Sensitivit (2)'!J8>0))="",FALSE,IF(ISERROR('Unit Economics & Sensitivit (2)'!J8>0),'Unit Economics & Sensitivit (2)'!J8>0,IF('Unit Economics & Sensitivit (2)'!J8="","",'Unit Economics & Sensitivit (2)'!J8>0))),CEILING('Unit Economics & Sensitivity ·'!B20/'Unit Economics & Sensitivit (2)'!J8,1),"") -> 14
A9: Full allowance use | B9: =1 -> 1 | C9: =1 -> 1 | D9: =0 -> 0 | E9: =1 -> 1 | F9: =('Unit Economics & Sensitivity ·'!B5*'Unit Economics & Sensitivit (2)'!B9+'Unit Economics & Sensitivity ·'!B6)*(1+MIN('Torque Assumptions · Run cost a'!B9*'Unit Economics & Sensitivit (2)'!C9,'Torque Assumptions · Run cost a'!B10)*'Torque Assumptions · Run cost a'!B11)+'Unit Economics & Sensitivity ·'!B10 -> 1.078 | G9: ='Torque Assumptions · Run cost a'!B17+'Unit Economics & Sensitivit (2)'!D9 -> 0.6 | H9: =IFERROR('Unit Economics & Sensitivit (2)'!F9/'Unit Economics & Sensitivit (2)'!G9,"") -> 1.7966667 | I9: =IF(IF(IF(ISERROR('Unit Economics & Sensitivit (2)'!E9=1),'Unit Economics & Sensitivit (2)'!E9=1,IF('Unit Economics & Sensitivit (2)'!E9="","",'Unit Economics & Sensitivit (2)'!E9=1))="",FALSE,IF(ISERROR('Unit Economics & Sensitivit (2)'!E9=1),'Unit Economics & Sensitivit (2)'!E9=1,IF('Unit Economics & Sensitivit (2)'!E9="","",'Unit Economics & Sensitivit (2)'!E9=1))),IF('Unit Economics & Sensitivity ·'!B16="","",'Unit Economics & Sensitivity ·'!B16),IF('Unit Economics & Sensitivity ·'!B15="","",'Unit Economics & Sensitivity ·'!B15)) -> 72.05 | J9: ='Unit Economics & Sensitivity ·'!B14-'Unit Economics & Sensitivit (2)'!I9*'Unit Economics & Sensitivit (2)'!F9-'Unit Economics & Sensitivity ·'!B14*'Torque Assumptions · Growth & o'!B13-'Torque Assumptions · Growth & o'!B14 -> 35.139462 | K9: =IFERROR('Unit Economics & Sensitivit (2)'!J9/'Unit Economics & Sensitivity ·'!B14,"") -> 0.30165865 | L9: =IF(IF(IF(ISERROR('Unit Economics & Sensitivit (2)'!J9>0),'Unit Economics & Sensitivit (2)'!J9>0,IF('Unit Economics & Sensitivit (2)'!J9="","",'Unit Economics & Sensitivit (2)'!J9>0))="",FALSE,IF(ISERROR('Unit Economics & Sensitivit (2)'!J9>0),'Unit Economics & Sensitivit (2)'!J9>0,IF('Unit Economics & Sensitivit (2)'!J9="","",'Unit Economics & Sensitivit (2)'!J9>0))),CEILING('Unit Economics & Sensitivity ·'!B20/'Unit Economics & Sensitivit (2)'!J9,1),"") -> 25
A10: All stresses combined | B10: =1.5 -> 1.5 | C10: =2 -> 2 | D10: =-0.15 -> -0.15 | E10: =1 -> 1 | F10: =('Unit Economics & Sensitivity ·'!B5*'Unit Economics & Sensitivit (2)'!B10+'Unit Economics & Sensitivity ·'!B6)*(1+MIN('Torque Assumptions · Run cost a'!B9*'Unit Economics & Sensitivit (2)'!C10,'Torque Assumptions · Run cost a'!B10)*'Torque Assumptions · Run cost a'!B11)+'Unit Economics & Sensitivity ·'!B10 -> 1.921 | G10: ='Torque Assumptions · Run cost a'!B17+'Unit Economics & Sensitivit (2)'!D10 -> 0.45 | H10: =IFERROR('Unit Economics & Sensitivit (2)'!F10/'Unit Economics & Sensitivit (2)'!G10,"") -> 4.2688889 | I10: =IF(IF(IF(ISERROR('Unit Economics & Sensitivit (2)'!E10=1),'Unit Economics & Sensitivit (2)'!E10=1,IF('Unit Economics & Sensitivit (2)'!E10="","",'Unit Economics & Sensitivit (2)'!E10=1))="",FALSE,IF(ISERROR('Unit Economics & Sensitivit (2)'!E10=1),'Unit Economics & Sensitivit (2)'!E10=1,IF('Unit Economics & Sensitivit (2)'!E10="","",'Unit Economics & Sensitivit (2)'!E10=1))),IF('Unit Economics & Sensitivity ·'!B16="","",'Unit Economics & Sensitivity ·'!B16),IF('Unit Economics & Sensitivity ·'!B15="","",'Unit Economics & Sensitivity ·'!B15)) -> 72.05 | J10: ='Unit Economics & Sensitivity ·'!B14-'Unit Economics & Sensitivit (2)'!I10*'Unit Economics & Sensitivit (2)'!F10-'Unit Economics & Sensitivity ·'!B14*'Torque Assumptions · Growth & o'!B13-'Torque Assumptions · Growth & o'!B14 -> -25.598688 | K10: =IFERROR('Unit Economics & Sensitivit (2)'!J10/'Unit Economics & Sensitivity ·'!B14,"") -> -0.2197548 | L10: =IF(IF(IF(ISERROR('Unit Economics & Sensitivit (2)'!J10>0),'Unit Economics & Sensitivit (2)'!J10>0,IF('Unit Economics & Sensitivit (2)'!J10="","",'Unit Economics & Sensitivit (2)'!J10>0))="",FALSE,IF(ISERROR('Unit Economics & Sensitivit (2)'!J10>0),'Unit Economics & Sensitivit (2)'!J10>0,IF('Unit Economics & Sensitivit (2)'!J10="","",'Unit Economics & Sensitivit (2)'!J10>0))),CEILING('Unit Economics & Sensitivity ·'!B20/'Unit Economics & Sensitivit (2)'!J10,1),"")

Sheet Torque Assumptions · Tier prici
A1: Torque Assumptions · Tier pricing & usage (assumptions)
A2: Financial model (4 pages) · Main Scenario
A4: Variable / dimension | B4: Monthly price | C4: Included issue runs | D4: Overage price per run | E4: Allowance used | F4: Overage runs per customer | G4: New customer mix | H4: Monthly churn rate | I4: Expected runs per customer | J4: Full allowance runs per customer | K4: Revenue per customer | L4: Mix weighted revenue | M4: Mix weighted expected runs | N4: Mix weighted full allowance runs
A5: Maintainer | B5: =29 -> 29 | C5: =20 -> 20 | D5: =2.5 -> 2.5 | E5: =0.55 -> 0.55 | F5: =0.5 -> 0.5 | G5: =0.5 -> 0.5 | H5: =0.08 -> 0.08 | I5: ='Torque Assumptions · Tier prici'!C5*'Torque Assumptions · Tier prici'!E5+'Torque Assumptions · Tier prici'!F5 -> 11.5 | J5: ='Torque Assumptions · Tier prici'!C5+'Torque Assumptions · Tier prici'!F5 -> 20.5 | K5: ='Torque Assumptions · Tier prici'!B5+'Torque Assumptions · Tier prici'!F5*'Torque Assumptions · Tier prici'!D5 -> 30.25 | L5: ='Torque Assumptions · Tier prici'!G5*'Torque Assumptions · Tier prici'!K5 -> 15.125 | M5: ='Torque Assumptions · Tier prici'!G5*'Torque Assumptions · Tier prici'!I5 -> 5.75 | N5: ='Torque Assumptions · Tier prici'!G5*'Torque Assumptions · Tier prici'!J5 -> 10.25
A6: Starter | B6: =99 -> 99 | C6: =60 -> 60 | D6: =2.25 -> 2.25 | E6: =0.6 -> 0.6 | F6: =3 -> 3 | G6: =0.35 -> 0.35 | H6: =0.05 -> 0.05 | I6: ='Torque Assumptions · Tier prici'!C6*'Torque Assumptions · Tier prici'!E6+'Torque Assumptions · Tier prici'!F6 -> 39 | J6: ='Torque Assumptions · Tier prici'!C6+'Torque Assumptions · Tier prici'!F6 -> 63 | K6: ='Torque Assumptions · Tier prici'!B6+'Torque Assumptions · Tier prici'!F6*'Torque Assumptions · Tier prici'!D6 -> 105.75 | L6: ='Torque Assumptions · Tier prici'!G6*'Torque Assumptions · Tier prici'!K6 -> 37.0125 | M6: ='Torque Assumptions · Tier prici'!G6*'Torque Assumptions · Tier prici'!I6 -> 13.65 | N6: ='Torque Assumptions · Tier prici'!G6*'Torque Assumptions · Tier prici'!J6 -> 22.05
A7: Team | B7: =399 -> 399 | C7: =250 -> 250 | D7: =2 -> 2 | E7: =0.65 -> 0.65 | F7: =15 -> 15 | G7: =0.15 -> 0.15 | H7: =0.03 -> 0.03 | I7: ='Torque Assumptions · Tier prici'!C7*'Torque Assumptions · Tier prici'!E7+'Torque Assumptions · Tier prici'!F7 -> 177.5 | J7: ='Torque Assumptions · Tier prici'!C7+'Torque Assumptions · Tier prici'!F7 -> 265 | K7: ='Torque Assumptions · Tier prici'!B7+'Torque Assumptions · Tier prici'!F7*'Torque Assumptions · Tier prici'!D7 -> 429 | L7: ='Torque Assumptions · Tier prici'!G7*'Torque Assumptions · Tier prici'!K7 -> 64.35 | M7: ='Torque Assumptions · Tier prici'!G7*'Torque Assumptions · Tier prici'!I7 -> 26.625 | N7: ='Torque Assumptions · Tier prici'!G7*'Torque Assumptions · Tier prici'!J7 -> 39.75

Sheet Torque Assumptions · Run cost a
A1: Torque Assumptions · Run cost assumptions
A2: Financial model (4 pages) · Main Scenario
A4: Variable / dimension | B4: Value
A5: Input tokens per attempt | B5: =150000 -> 150000
A6: Output tokens per attempt | B6: =20000 -> 20000
A7: Input token price per 1M | B7: =3 -> 3
A8: Output token price per 1M | B8: =15 -> 15
A9: Average recovery retries per run | B9: =0.6 -> 0.6
A10: Retry limit per run | B10: =2 -> 2
A11: Retry cost vs first attempt | B11: =0.5 -> 0.5
A12: Sandbox minutes per attempt | B12: =15 -> 15
A13: Sandbox cost per minute | B13: =0.004 -> 0.004
A14: Tracing cost per run neatlogs | B14: =0.01 -> 0.01
A15: Context and checkpoint cost per run Entire | B15: =0.01 -> 0.01
A16: Storage cost per run | B16: =0.005 -> 0.005
A17: Verified success rate | B17: =0.6 -> 0.6

Sheet Torque Assumptions · Growth & o
A1: Torque Assumptions · Growth & operating assumptions
A2: Financial model (4 pages) · Main Scenario
A4: Variable / dimension | B4: Value
A5: New customers in launch month | B5: =3 -> 3
A6: Monthly growth in new customers | B6: =0.25 -> 0.25
A7: Fixed hosting per month | B7: =150 -> 150
A8: Software and tools per month | B8: =200 -> 200
A9: Marketing per month | B9: =500 -> 500
A10: Team expenses per month | B10: =0 -> 0
A11: Starting cash | B11: =0 -> 0
A12: Target gross margin | B12: =0.65 -> 0.65
A13: Payment processing rate | B13: =0.029 -> 0.029
A14: Payment fee per charge | B14: =0.3 -> 0.3

Sheet Model inputs
A1: Model inputs
A2: Integration values are aggregated snapshots; raw source records are not included.
A4: Variables
A5: Variable / segment | B5: Value | C5: Value | D5: 2026-09 | E5: 2026-10 | F5: 2026-11 | G5: 2026-12 | H5: 2027-01 | I5: 2027-02 | J5: 2027-03 | K5: 2027-04 | L5: 2027-05 | M5: 2027-06 | N5: 2027-07 | O5: 2027-08 | P5: 2027-09 | Q5: 2026-01 | R5: 2026-02 | S5: 2026-03 | T5: 2026-04 | U5: 2026-05 | V5: 2026-06 | W5: 2026-07 | X5: 2026-08
A6: Blended full allowance runs per customer | B6: =SUM('Model inputs'!C48,'Model inputs'!C49,'Model inputs'!C50) -> 72.05
A7: Blended revenue per customer · Unit Economics & Sensitivity · Unit economics per issue run | C7: =SUM('Model inputs'!C52,'Model inputs'!C53,'Model inputs'!C54) -> 116.4875
A8: Blended revenue per customer · Unit Economics & Sensitivity · Sensitivity: cost and margin stress tests | B8: =SUM('Model inputs'!C52,'Model inputs'!C53,'Model inputs'!C54) -> 116.4875
A9: Blended runs per customer · Unit Economics & Sensitivity · Unit economics per issue run | C9: =SUM('Model inputs'!C44,'Model inputs'!C45,'Model inputs'!C46) -> 46.025
A10: Blended runs per customer · Unit Economics & Sensitivity · Sensitivity: cost and margin stress tests | B10: =SUM('Model inputs'!C44,'Model inputs'!C45,'Model inputs'!C46) -> 46.025
A11: Cash balance after credits | D11: =IF('Torque Assumptions · Growth & o'!B11="","",'Torque Assumptions · Growth & o'!B11) -> 0 | E11: ='Model inputs'!D11+'Model inputs'!E56 -> -615.41676 | F11: ='Model inputs'!E11+'Model inputs'!F56 -> -1047.0598 | G11: ='Model inputs'!F11+'Model inputs'!G56 -> -1200.5315 | H11: ='Model inputs'!G11+'Model inputs'!H56 -> -1013.6987 | I11: ='Model inputs'!H11+'Model inputs'!I56 -> -408.53069 | J11: ='Model inputs'!I11+'Model inputs'!J56 -> 712.85438 | K11: ='Model inputs'!J11+'Model inputs'!K56 -> 2473.1332 | L11: ='Model inputs'!K11+'Model inputs'!L56 -> 5025.958 | ... P11: ='Model inputs'!O11+'Model inputs'!P56 -> 27810.715
A12: Cash balance before credits | D12: =IF('Torque Assumptions · Growth & o'!B11="","",'Torque Assumptions · Growth & o'!B11) -> 0 | E12: ='Model inputs'!D12+'Model inputs'!E57 -> -660.41676 | F12: ='Model inputs'!E12+'Model inputs'!F57 -> -1092.0598 | G12: ='Model inputs'!F12+'Model inputs'!G57 -> -1245.5315 | H12: ='Model inputs'!G12+'Model inputs'!H57 -> -1058.6987 | I12: ='Model inputs'!H12+'Model inputs'!I57 -> -453.53069 | J12: ='Model inputs'!I12+'Model inputs'!J57 -> 667.85438 | K12: ='Model inputs'!J12+'Model inputs'!K57 -> 2428.1332 | L12: ='Model inputs'!K12+'Model inputs'!L57 -> 4980.958 | ... P12: ='Model inputs'!O12+'Model inputs'!P57 -> 27765.715
A13: Cost of revenue | D13: 0 | E13: ='Model inputs'!E37+'Model inputs'!E91+'Model inputs'!E60+'Model inputs'!E97+'Model inputs'!E22+'Model inputs'!E88 -> 309.87926 | F13: ='Model inputs'!F37+'Model inputs'!F91+'Model inputs'!F60+'Model inputs'!F97+'Model inputs'!F22+'Model inputs'!F88 -> 502.96031 | G13: ='Model inputs'!G37+'Model inputs'!G91+'Model inputs'!G60+'Model inputs'!G97+'Model inputs'!G22+'Model inputs'!G88 -> 737.87576 | H13: ='Model inputs'!H37+'Model inputs'!H91+'Model inputs'!H60+'Model inputs'!H97+'Model inputs'!H22+'Model inputs'!H88 -> 1025.3975 | I13: ='Model inputs'!I37+'Model inputs'!I91+'Model inputs'!I60+'Model inputs'!I97+'Model inputs'!I22+'Model inputs'!I88 -> 1378.9728 | J13: ='Model inputs'!J37+'Model inputs'!J91+'Model inputs'!J60+'Model inputs'!J97+'Model inputs'!J22+'Model inputs'!J88 -> 1815.394 | K13: ='Model inputs'!K37+'Model inputs'!K91+'Model inputs'!K60+'Model inputs'!K97+'Model inputs'!K22+'Model inputs'!K88 -> 2355.6364 | L13: ='Model inputs'!L37+'Model inputs'!L91+'Model inputs'!L60+'Model inputs'!L97+'Model inputs'!L22+'Model inputs'!L88 -> 3025.9043 | ... P13: ='Model inputs'!P37+'Model inputs'!P91+'Model inputs'!P60+'Model inputs'!P97+'Model inputs'!P22+'Model inputs'!P88 -> 7797.433
A14: Fixed monthly costs · Unit Economics & Sensitivity · Unit economics per issue run | C14: ='Model inputs'!B132+'Model inputs'!B156+'Model inputs'!B140+'Model inputs'!B160 -> 850
A15: Fixed monthly costs · Unit Economics & Sensitivity · Sensitivity: cost and margin stress tests | B15: ='Model inputs'!B132+'Model inputs'!B156+'Model inputs'!B140+'Model inputs'!B160 -> 850
A16: Gross profit after credits | D16: 0 | E16: ='Model inputs'!E17+'Model inputs'!E20 -> 84.583237 | F16: ='Model inputs'!F17+'Model inputs'!F20 -> 268.35694 | G16: ='Model inputs'!G17+'Model inputs'!G20 -> 546.5283 | H16: ='Model inputs'!H17+'Model inputs'!H20 -> 886.83283 | I16: ='Model inputs'!I17+'Model inputs'!I20 -> 1305.168 | J16: ='Model inputs'!J17+'Model inputs'!J20 -> 1821.3851 | K16: ='Model inputs'!K17+'Model inputs'!K20 -> 2460.2788 | L16: ='Model inputs'!L17+'Model inputs'!L20 -> 3252.8248 | ... P16: ='Model inputs'!P17+'Model inputs'!P20 -> 8893.5743
A17: Gross profit before credits · Torque Plan Summary · Scenario comparison: month 12 (Sep 2027) · Main Scenario | D17: 0 | E17: ='Model inputs'!E121-'Model inputs'!E13 -> 39.583237 | F17: ='Model inputs'!F121-'Model inputs'!F13 -> 268.35694 | G17: ='Model inputs'!G121-'Model inputs'!G13 -> 546.5283 | H17: ='Model inputs'!H121-'Model inputs'!H13 -> 886.83283 | I17: ='Model inputs'!I121-'Model inputs'!I13 -> 1305.168 | J17: ='Model inputs'!J121-'Model inputs'!J13 -> 1821.3851 | K17: ='Model inputs'!K121-'Model inputs'!K13 -> 2460.2788 | L17: ='Model inputs'!L121-'Model inputs'!L13 -> 3252.8248 | ... P17: ='Model inputs'!P121-'Model inputs'!P13 -> 8893.5743
A18: Gross profit before credits · Optimistic | P18: ='Torque Plan Summary · Scenario'!D7-'Torque Plan Summary · Scenario'!D8 -> 30263.98
A19: Gross profit before credits · Conservative | P19: ='Torque Plan Summary · Scenario'!C7-'Torque Plan Summary · Scenario'!C8 -> 946.16924
A20: Hackathon credits applied | D20: 0 | E20: =MIN('Model inputs'!E21,'Model inputs'!E37+'Model inputs'!E91) -> 45 | F20: =MIN('Model inputs'!F21,'Model inputs'!F37+'Model inputs'!F91) -> 0 | G20: =MIN('Model inputs'!G21,'Model inputs'!G37+'Model inputs'!G91) -> 0 | H20: =MIN('Model inputs'!H21,'Model inputs'!H37+'Model inputs'!H91) -> 0 | I20: =MIN('Model inputs'!I21,'Model inputs'!I37+'Model inputs'!I91) -> 0 | J20: =MIN('Model inputs'!J21,'Model inputs'!J37+'Model inputs'!J91) -> 0 | K20: =MIN('Model inputs'!K21,'Model inputs'!K37+'Model inputs'!K91) -> 0 | L20: =MIN('Model inputs'!L21,'Model inputs'!L37+'Model inputs'!L91) -> 0 | ... P20: =MIN('Model inputs'!P21,'Model inputs'!P37+'Model inputs'!P91) -> 0
A21: Hackathon credits available | D21: 0 | E21: ='Monthly Financial Plan · Torque'!B37 -> 45 | F21: ='Monthly Financial Plan · Torque'!C37 -> 0 | G21: ='Monthly Financial Plan · Torque'!D37 -> 0 | H21: 0 | I21: 0 | J21: 0 | K21: 0 | L21: 0 | M21: 0 | N21: 0 | O21: 0 | P21: 0
A22: Hosting cost · Torque Plan Summary · Scenario comparison: month 12 (Sep 2027) · Main Scenario | D22: 0 | E22: =IF('Model inputs'!B132="","",'Model inputs'!B132) -> 150 | F22: =IF('Model inputs'!B132="","",'Model inputs'!B132) -> 150 | G22: =IF('Model inputs'!B132="","",'Model inputs'!B132) -> 150 | H22: =IF('Model inputs'!B132="","",'Model inputs'!B132) -> 150 | I22: =IF('Model inputs'!B132="","",'Model inputs'!B132) -> 150 | J22: =IF('Model inputs'!B132="","",'Model inputs'!B132) -> 150 | K22: =IF('Model inputs'!B132="","",'Model inputs'!B132) -> 150 | L22: =IF('Model inputs'!B132="","",'Model inputs'!B132) -> 150 | M22: =IF('Model inputs'!B132="","",'Model inputs'!B132) -> 150 | N22: =IF('Model inputs'!B132="","",'Model inputs'!B132) -> 150 | O22: =IF('Model inputs'!B132="","",'Model inputs'!B132) -> 150 | P22: =IF('Model inputs'!B132="","",'Model inputs'!B132) -> 150
A23: Hosting cost · Optimistic | P23: =IF('Model inputs'!B219="","",'Model inputs'!B219) -> 150
A24: Hosting cost · Conservative | P24: =IF('Model inputs'!B220="","",'Model inputs'!B220) -> 150
A25: Issue runs | D25: =SUM('Model inputs'!D26,'Model inputs'!D27,'Model inputs'!D28) -> 0 | E25: =SUM('Model inputs'!E26,'Model inputs'!E27,'Model inputs'!E28) -> 138.075 | F25: =SUM('Model inputs'!F26,'Model inputs'!F27,'Model inputs'!F28) -> 304.845 | G25: =SUM('Model inputs'!G26,'Model inputs'!G27,'Model inputs'!G28) -> 507.76841 | H25: =SUM('Model inputs'!H26,'Model inputs'!H27,'Model inputs'!H28) -> 756.15215 | I25: =SUM('Model inputs'!I26,'Model inputs'!I27,'Model inputs'!I28) -> 1061.6148 | J25: =SUM('Model inputs'!J26,'Model inputs'!J27,'Model inputs'!J28) -> 1438.6653 | K25: =SUM('Model inputs'!K26,'Model inputs'!K27,'Model inputs'!K28) -> 1905.4269 | ... P25: =SUM('Model inputs'!P26,'Model inputs'!P27,'Model inputs'!P28) -> 6607.2894
A26: Issue runs > Maintainer | D26: =0 -> 0 | E26: ='Model inputs'!E77*'Model inputs'!B129 -> 17.25 | F26: ='Model inputs'!F77*'Model inputs'!B129 -> 37.4325 | G26: ='Model inputs'!G77*'Model inputs'!B129 -> 61.391025 | H26: ='Model inputs'!H77*'Model inputs'!B129 -> 90.171149 | I26: ='Model inputs'!I77*'Model inputs'!B129 -> 125.07172 | J26: ='Model inputs'!J77*'Model inputs'!B129 -> 167.7088 | K26: ='Model inputs'!K77*'Model inputs'!B129 -> 220.09562 | L26: ='Model inputs'!L77*'Model inputs'!B129 -> 284.74238 | M26: ='Model inputs'!M77*'Model inputs'!B129 -> 364.78101 | N26: ='Model inputs'!N77*'Model inputs'!B129 -> 464.12104 | O26: ='Model inputs'!O77*'Model inputs'!B129 -> 587.6445 | P26: ='Model inputs'!P77*'Model inputs'!B129 -> 741.44937
A27: Issue runs > Starter | D27: =0 -> 0 | E27: ='Model inputs'!E78*'Model inputs'!B130 -> 40.95 | F27: ='Model inputs'!F78*'Model inputs'!B130 -> 90.09 | G27: ='Model inputs'!G78*'Model inputs'!B130 -> 149.56987 | H27: ='Model inputs'!H78*'Model inputs'!B130 -> 222.07185 | I27: ='Model inputs'!I78*'Model inputs'!B130 -> 310.94384 | J27: ='Model inputs'!J78*'Model inputs'!B130 -> 420.36613 | K27: ='Model inputs'!K78*'Model inputs'!B130 -> 555.55968 | L27: ='Model inputs'!L78*'Model inputs'!B130 -> 723.04651 | M27: ='Model inputs'!M78*'Model inputs'!B130 -> 930.97521 | N27: ='Model inputs'!N78*'Model inputs'!B130 -> 1189.5277 | O27: ='Model inputs'!O78*'Model inputs'!B130 -> 1511.4279 | P27: ='Model inputs'!P78*'Model inputs'!B130 -> 1912.5773
A28: Issue runs > Team | D28: =0 -> 0 | E28: ='Model inputs'!E79*'Model inputs'!B131 -> 79.875 | F28: ='Model inputs'!F79*'Model inputs'!B131 -> 177.3225 | G28: ='Model inputs'!G79*'Model inputs'!B131 -> 296.80751 | H28: ='Model inputs'!H79*'Model inputs'!B131 -> 443.90915 | I28: ='Model inputs'!I79*'Model inputs'!B131 -> 625.5992 | J28: ='Model inputs'!J79*'Model inputs'!B131 -> 850.59038 | K28: ='Model inputs'!K79*'Model inputs'!B131 -> 1129.7716 | L28: ='Model inputs'!L79*'Model inputs'!B131 -> 1476.7521 | M28: ='Model inputs'!M79*'Model inputs'!B131 -> 1908.5417 | N28: ='Model inputs'!N79*'Model inputs'!B131 -> 2446.4006 | O28: ='Model inputs'!O79*'Model inputs'!B131 -> 3116.9024 | P28: ='Model inputs'!P79*'Model inputs'!B131 -> 3953.2628
A29: Issue runs | P29: =SUM('Model inputs'!P30,'Model inputs'!P31,'Model inputs'!P32) -> 15314.438
A30: Issue runs > Maintainer | P30: ='Model inputs'!P81*'Model inputs'!B212 -> 1719.1639
A31: Issue runs > Starter | P31: ='Model inputs'!P82*'Model inputs'!B213 -> 4446.0053
A32: Issue runs > Team | P32: ='Model inputs'!P83*'Model inputs'!B214 -> 9149.2687
A33: Issue runs | P33: =SUM('Model inputs'!P34,'Model inputs'!P35,'Model inputs'!P36) -> 1930.3822
A34: Issue runs > Maintainer | P34: ='Model inputs'!P85*'Model inputs'!B216 -> 221.07215
A35: Issue runs > Starter | P35: ='Model inputs'!P86*'Model inputs'!B217 -> 545.91787
A36: Issue runs > Team | P36: ='Model inputs'!P87*'Model inputs'!B218 -> 1163.3921
A37: LLM token cost · Torque Plan Summary · Scenario comparison: month 12 (Sep 2027) · Main Scenario | D37: 0 | E37: =SUM('Model inputs'!E26,'Model inputs'!E27,'Model inputs'!E28)*'Model inputs'!B138 -> 134.62312 | F37: =SUM('Model inputs'!F26,'Model inputs'!F27,'Model inputs'!F28)*'Model inputs'!B138 -> 297.22388 | G37: =SUM('Model inputs'!G26,'Model inputs'!G27,'Model inputs'!G28)*'Model inputs'!B138 -> 495.0742 | H37: =SUM('Model inputs'!H26,'Model inputs'!H27,'Model inputs'!H28)*'Model inputs'!B138 -> 737.24834 | I37: =SUM('Model inputs'!I26,'Model inputs'!I27,'Model inputs'!I28)*'Model inputs'!B138 -> 1035.0744 | J37: =SUM('Model inputs'!J26,'Model inputs'!J27,'Model inputs'!J28)*'Model inputs'!B138 -> 1402.6987 | K37: =SUM('Model inputs'!K26,'Model inputs'!K27,'Model inputs'!K28)*'Model inputs'!B138 -> 1857.7912 | L37: =SUM('Model inputs'!L26,'Model inputs'!L27,'Model inputs'!L28)*'Model inputs'!B138 -> 2422.4275 | M37: =SUM('Model inputs'!M26,'Model inputs'!M27,'Model inputs'!M28)*'Model inputs'!B138 -> 3124.1904 | N37: =SUM('Model inputs'!N26,'Model inputs'!N27,'Model inputs'!N28)*'Model inputs'!B138 -> 3997.5481 | O37: =SUM('Model inputs'!O26,'Model inputs'!O27,'Model inputs'!O28)*'Model inputs'!B138 -> 5085.5755 | P37: =SUM('Model inputs'!P26,'Model inputs'!P27,'Model inputs'!P28)*'Model inputs'!B138 -> 6442.1072
A38: LLM token cost · Optimistic | P38: =SUM('Model inputs'!P30,'Model inputs'!P31,'Model inputs'!P32)*'Model inputs'!B221 -> 12129.035
A39: LLM token cost · Conservative | P39: =SUM('Model inputs'!P34,'Model inputs'!P35,'Model inputs'!P36)*'Model inputs'!B222 -> 2519.1487
A40: Marketing · Torque Plan Summary · Scenario comparison: month 12 (Sep 2027) · Main Scenario | D40: 0 | E40: =IF('Model inputs'!B140="","",'Model inputs'!B140) -> 500 | F40: =IF('Model inputs'!B140="","",'Model inputs'!B140) -> 500 | G40: =IF('Model inputs'!B140="","",'Model inputs'!B140) -> 500 | H40: =IF('Model inputs'!B140="","",'Model inputs'!B140) -> 500 | I40: =IF('Model inputs'!B140="","",'Model inputs'!B140) -> 500 | J40: =IF('Model inputs'!B140="","",'Model inputs'!B140) -> 500 | K40: =IF('Model inputs'!B140="","",'Model inputs'!B140) -> 500 | L40: =IF('Model inputs'!B140="","",'Model inputs'!B140) -> 500 | M40: =IF('Model inputs'!B140="","",'Model inputs'!B140) -> 500 | N40: =IF('Model inputs'!B140="","",'Model inputs'!B140) -> 500 | O40: =IF('Model inputs'!B140="","",'Model inputs'!B140) -> 500 | P40: =IF('Model inputs'!B140="","",'Model inputs'!B140) -> 500
A41: Marketing · Optimistic | P41: =IF('Model inputs'!B223="","",'Model inputs'!B223) -> 500
A42: Marketing · Conservative | P42: =IF('Model inputs'!B224="","",'Model inputs'!B224) -> 500
A43: Mix weighted expected runs | C43: ='Model inputs'!B142*'Model inputs'!B128 -> 0
A44: Mix weighted expected runs > Maintainer | C44: ='Model inputs'!B143*'Model inputs'!B129 -> 5.75
A45: Mix weighted expected runs > Starter | C45: ='Model inputs'!B144*'Model inputs'!B130 -> 13.65
A46: Mix weighted expected runs > Team | C46: ='Model inputs'!B145*'Model inputs'!B131 -> 26.625
A47: Mix weighted full allowance runs | C47: ='Model inputs'!B142*'Model inputs'!B134 -> 0
A48: Mix weighted full allowance runs > Maintainer | C48: ='Model inputs'!B143*'Model inputs'!B135 -> 10.25
A49: Mix weighted full allowance runs > Starter | C49: ='Model inputs'!B144*'Model inputs'!B136 -> 22.05
A50: Mix weighted full allowance runs > Team | C50: ='Model inputs'!B145*'Model inputs'!B137 -> 39.75
A51: Mix weighted revenue | C51: ='Model inputs'!B142*'Model inputs'!B150 -> 0
A52: Mix weighted revenue > Maintainer | C52: ='Model inputs'!B143*'Model inputs'!B151 -> 15.125
A53: Mix weighted revenue > Starter | C53: ='Model inputs'!B144*'Model inputs'!B152 -> 37.0125
A54: Mix weighted revenue > Team | C54: ='Model inputs'!B145*'Model inputs'!B153 -> 64.35
A55: Monthly growth in new customers | B55: ='Torque Assumptions · Growth & o'!B6 -> 0.25
A56: Net cash flow after credits | D56: 0 | E56: ='Model inputs'!E16-'Model inputs'!E63 -> -615.41676 | F56: ='Model inputs'!F16-'Model inputs'!F63 -> -431.64306 | G56: ='Model inputs'!G16-'Model inputs'!G63 -> -153.4717 | H56: ='Model inputs'!H16-'Model inputs'!H63 -> 186.83283 | I56: ='Model inputs'!I16-'Model inputs'!I63 -> 605.168 | J56: ='Model inputs'!J16-'Model inputs'!J63 -> 1121.3851 | K56: ='Model inputs'!K16-'Model inputs'!K63 -> 1760.2788 | L56: ='Model inputs'!L16-'Model inputs'!L63 -> 2552.8248 | ... P56: ='Model inputs'!P16-'Model inputs'!P63 -> 8193.5743
A57: Net cash flow before credits | D57: 0 | E57: ='Model inputs'!E17-'Model inputs'!E63 -> -660.41676 | F57: ='Model inputs'!F17-'Model inputs'!F63 -> -431.64306 | G57: ='Model inputs'!G17-'Model inputs'!G63 -> -153.4717 | H57: ='Model inputs'!H17-'Model inputs'!H63 -> 186.83283 | I57: ='Model inputs'!I17-'Model inputs'!I63 -> 605.168 | J57: ='Model inputs'!J17-'Model inputs'!J63 -> 1121.3851 | K57: ='Model inputs'!K17-'Model inputs'!K63 -> 1760.2788 | L57: ='Model inputs'!L17-'Model inputs'!L63 -> 2552.8248 | ... P57: ='Model inputs'!P17-'Model inputs'!P63 -> 8193.5743
A58: New customers | D58: 0 | E58: ='Model inputs'!B59*IF(AND((1+'Model inputs'!B55)=0,DATEDIF(DATE(2026,10,1),DATE(2026,10,1),"M")=0),SQRT(-1),(1+'Model inputs'!B55)^DATEDIF(DATE(2026,10,1),DATE(2026,10,1),"M")) -> 3 | F58: ='Model inputs'!B59*IF(AND((1+'Model inputs'!B55)=0,DATEDIF(DATE(2026,10,1),DATE(2026,11,1),"M")=0),SQRT(-1),(1+'Model inputs'!B55)^DATEDIF(DATE(2026,10,1),DATE(2026,11,1),"M")) -> 3.75 | G58: ='Model inputs'!B59*IF(AND((1+'Model inputs'!B55)=0,DATEDIF(DATE(2026,10,1),DATE(2026,12,1),"M")=0),SQRT(-1),(1+'Model inputs'!B55)^DATEDIF(DATE(2026,10,1),DATE(2026,12,1),"M")) -> 4.6875 | H58: ='Model inputs'!B59*IF(AND((1+'Model inputs'!B55)=0,DATEDIF(DATE(2026,10,1),DATE(2027,1,1),"M")=0),SQRT(-1),(1+'Model inputs'!B55)^DATEDIF(DATE(2026,10,1),DATE(2027,1,1),"M")) -> 5.859375 | I58: ='Model inputs'!B59*IF(AND((1+'Model inputs'!B55)=0,DATEDIF(DATE(2026,10,1),DATE(2027,2,1),"M")=0),SQRT(-1),(1+'Model inputs'!B55)^DATEDIF(DATE(2026,10,1),DATE(2027,2,1),"M")) -> 7.3242188 | J58: ='Model inputs'!B59*IF(AND((1+'Model inputs'!B55)=0,DATEDIF(DATE(2026,10,1),DATE(2027,3,1),"M")=0),SQRT(-1),(1+'Model inputs'!B55)^DATEDIF(DATE(2026,10,1),DATE(2027,3,1),"M")) -> 9.1552734 | K58: ='Model inputs'!B59*IF(AND((1+'Model inputs'!B55)=0,DATEDIF(DATE(2026,10,1),DATE(2027,4,1),"M")=0),SQRT(-1),(1+'Model inputs'!B55)^DATEDIF(DATE(2026,10,1),DATE(2027,4,1),"M")) -> 11.444092 | L58: ='Model inputs'!B59*IF(AND((1+'Model inputs'!B55)=0,DATEDIF(DATE(2026,10,1),DATE(2027,5,1),"M")=0),SQRT(-1),(1+'Model inputs'!B55)^DATEDIF(DATE(2026,10,1),DATE(2027,5,1),"M")) -> 14.305115 | M58: ='Model inputs'!B59*IF(AND((1+'Model inputs'!B55)=0,DATEDIF(DATE(2026,10,1),DATE(2027,6,1),"M")=0),SQRT(-1),(1+'Model inputs'!B55)^DATEDIF(DATE(2026,10,1),DATE(2027,6,1),"M")) -> 17.881393 | N58: ='Model inputs'!B59*IF(AND((1+'Model inputs'!B55)=0,DATEDIF(DATE(2026,10,1),DATE(2027,7,1),"M")=0),SQRT(-1),(1+'Model inputs'!B55)^DATEDIF(DATE(2026,10,1),DATE(2027,7,1),"M")) -> 22.351742 | O58: ='Model inputs'!B59*IF(AND((1+'Model inputs'!B55)=0,DATEDIF(DATE(2026,10,1),DATE(2027,8,1),"M")=0),SQRT(-1),(1+'Model inputs'!B55)^DATEDIF(DATE(2026,10,1),DATE(2027,8,1),"M")) -> 27.939677 | P58: ='Model inputs'!B59*IF(AND((1+'Model inputs'!B55)=0,DATEDIF(DATE(2026,10,1),DATE(2027,9,1),"M")=0),SQRT(-1),(1+'Model inputs'!B55)^DATEDIF(DATE(2026,10,1),DATE(2027,9,1),"M")) -> 34.924597
A59: New customers in launch month | B59: ='Torque Assumptions · Growth & o'!B5 -> 3
A60: Observability and context cost · Torque Plan Summary · Scenario comparison: month 12 (Sep 2027) · Main Scenario | D60: 0 | E60: =SUM('Model inputs'!E26,'Model inputs'!E27,'Model inputs'!E28)*('Model inputs'!B162+'Model inputs'!B126) -> 2.7615 | F60: =SUM('Model inputs'!F26,'Model inputs'!F27,'Model inputs'!F28)*('Model inputs'!B162+'Model inputs'!B126) -> 6.0969 | G60: =SUM('Model inputs'!G26,'Model inputs'!G27,'Model inputs'!G28)*('Model inputs'!B162+'Model inputs'!B126) -> 10.155368 | H60: =SUM('Model inputs'!H26,'Model inputs'!H27,'Model inputs'!H28)*('Model inputs'!B162+'Model inputs'!B126) -> 15.123043 | I60: =SUM('Model inputs'!I26,'Model inputs'!I27,'Model inputs'!I28)*('Model inputs'!B162+'Model inputs'!B126) -> 21.232295 | J60: =SUM('Model inputs'!J26,'Model inputs'!J27,'Model inputs'!J28)*('Model inputs'!B162+'Model inputs'!B126) -> 28.773306 | K60: =SUM('Model inputs'!K26,'Model inputs'!K27,'Model inputs'!K28)*('Model inputs'!B162+'Model inputs'!B126) -> 38.108538 | L60: =SUM('Model inputs'!L26,'Model inputs'!L27,'Model inputs'!L28)*('Model inputs'!B162+'Model inputs'!B126) -> 49.690821 | M60: =SUM('Model inputs'!M26,'Model inputs'!M27,'Model inputs'!M28)*('Model inputs'!B162+'Model inputs'!B126) -> 64.085958 | N60: =SUM('Model inputs'!N26,'Model inputs'!N27,'Model inputs'!N28)*('Model inputs'!B162+'Model inputs'!B126) -> 82.000986 | O60: =SUM('Model inputs'!O26,'Model inputs'!O27,'Model inputs'!O28)*('Model inputs'!B162+'Model inputs'!B126) -> 104.3195 | P60: =SUM('Model inputs'!P26,'Model inputs'!P27,'Model inputs'!P28)*('Model inputs'!B162+'Model inputs'!B126) -> 132.14579
A61: Observability and context cost · Optimistic | P61: =SUM('Model inputs'!P30,'Model inputs'!P31,'Model inputs'!P32)*('Model inputs'!B307+'Model inputs'!B205) -> 306.28876
A62: Observability and context cost · Conservative | P62: =SUM('Model inputs'!P34,'Model inputs'!P35,'Model inputs'!P36)*('Model inputs'!B308+'Model inputs'!B206) -> 38.607643
A63: Operating expenses · Torque Plan Summary · Scenario comparison: month 12 (Sep 2027) | D63: 0 | E63: ='Model inputs'!E116+'Model inputs'!E94+'Model inputs'!E40 -> 700 | F63: ='Model inputs'!F116+'Model inputs'!F94+'Model inputs'!F40 -> 700 | G63: ='Model inputs'!G116+'Model inputs'!G94+'Model inputs'!G40 -> 700 | H63: ='Model inputs'!H116+'Model inputs'!H94+'Model inputs'!H40 -> 700 | I63: ='Model inputs'!I116+'Model inputs'!I94+'Model inputs'!I40 -> 700 | J63: ='Model inputs'!J116+'Model inputs'!J94+'Model inputs'!J40 -> 700 | K63: ='Model inputs'!K116+'Model inputs'!K94+'Model inputs'!K40 -> 700 | L63: ='Model inputs'!L116+'Model inputs'!L94+'Model inputs'!L40 -> 700 | ... P63: ='Model inputs'!P116+'Model inputs'!P94+'Model inputs'!P40 -> 700
A64: Overage revenue | D64: =SUM('Model inputs'!D65,'Model inputs'!D66,'Model inputs'!D67) -> 0 | E64: =SUM('Model inputs'!E65,'Model inputs'!E66,'Model inputs'!E67) -> 22.4625 | F64: =SUM('Model inputs'!F65,'Model inputs'!F66,'Model inputs'!F67) -> 49.63125 | G64: =SUM('Model inputs'!G65,'Model inputs'!G66,'Model inputs'!G67) -> 82.724681 | H64: =SUM('Model inputs'!H65,'Model inputs'!H66,'Model inputs'!H67) -> 123.26362 | I64: =SUM('Model inputs'!I65,'Model inputs'!I66,'Model inputs'!I67) -> 173.14703 | J64: =SUM('Model inputs'!J65,'Model inputs'!J66,'Model inputs'!J67) -> 234.74665 | K64: =SUM('Model inputs'!K65,'Model inputs'!K66,'Model inputs'!K67) -> 311.02531 | ... P64: =SUM('Model inputs'!P65,'Model inputs'!P66,'Model inputs'!P67) -> 1079.7724
A65: Overage revenue > Maintainer | D65: =0 -> 0 | E65: ='Model inputs'!E77*'Model inputs'!B184*'Model inputs'!B180 -> 1.875 | F65: ='Model inputs'!F77*'Model inputs'!B184*'Model inputs'!B180 -> 4.06875 | G65: ='Model inputs'!G77*'Model inputs'!B184*'Model inputs'!B180 -> 6.6729375 | H65: ='Model inputs'!H77*'Model inputs'!B184*'Model inputs'!B180 -> 9.8012119 | I65: ='Model inputs'!I77*'Model inputs'!B184*'Model inputs'!B180 -> 13.594752 | J65: ='Model inputs'!J77*'Model inputs'!B184*'Model inputs'!B180 -> 18.229217 | K65: ='Model inputs'!K77*'Model inputs'!B184*'Model inputs'!B180 -> 23.923437 | L65: ='Model inputs'!L77*'Model inputs'!B184*'Model inputs'!B180 -> 30.950259 | M65: ='Model inputs'!M77*'Model inputs'!B184*'Model inputs'!B180 -> 39.650109 | N65: ='Model inputs'!N77*'Model inputs'!B184*'Model inputs'!B180 -> 50.447939 | O65: ='Model inputs'!O77*'Model inputs'!B184*'Model inputs'!B180 -> 63.874402 | P65: ='Model inputs'!P77*'Model inputs'!B184*'Model inputs'!B180 -> 80.592323
A66: Overage revenue > Starter | D66: =0 -> 0 | E66: ='Model inputs'!E78*'Model inputs'!B185*'Model inputs'!B181 -> 7.0875 | F66: ='Model inputs'!F78*'Model inputs'!B185*'Model inputs'!B181 -> 15.5925 | G66: ='Model inputs'!G78*'Model inputs'!B185*'Model inputs'!B181 -> 25.887094 | H66: ='Model inputs'!H78*'Model inputs'!B185*'Model inputs'!B181 -> 38.435512 | I66: ='Model inputs'!I78*'Model inputs'!B185*'Model inputs'!B181 -> 53.817204 | J66: ='Model inputs'!J78*'Model inputs'!B185*'Model inputs'!B181 -> 72.755677 | K66: ='Model inputs'!K78*'Model inputs'!B185*'Model inputs'!B181 -> 96.15456 | L66: ='Model inputs'!L78*'Model inputs'!B185*'Model inputs'!B181 -> 125.14267 | M66: ='Model inputs'!M78*'Model inputs'!B185*'Model inputs'!B181 -> 161.13032 | N66: ='Model inputs'!N78*'Model inputs'!B185*'Model inputs'!B181 -> 205.8798 | O66: ='Model inputs'!O78*'Model inputs'!B185*'Model inputs'!B181 -> 261.5933 | P66: ='Model inputs'!P78*'Model inputs'!B185*'Model inputs'!B181 -> 331.02299
A67: Overage revenue > Team | D67: =0 -> 0 | E67: ='Model inputs'!E79*'Model inputs'!B186*'Model inputs'!B182 -> 13.5 | F67: ='Model inputs'!F79*'Model inputs'!B186*'Model inputs'!B182 -> 29.97 | G67: ='Model inputs'!G79*'Model inputs'!B186*'Model inputs'!B182 -> 50.16465 | H67: ='Model inputs'!H79*'Model inputs'!B186*'Model inputs'!B182 -> 75.026898 | I67: ='Model inputs'!I79*'Model inputs'!B186*'Model inputs'!B182 -> 105.73508 | J67: ='Model inputs'!J79*'Model inputs'!B186*'Model inputs'!B182 -> 143.76175 | K67: ='Model inputs'!K79*'Model inputs'!B186*'Model inputs'!B182 -> 190.94731 | L67: ='Model inputs'!L79*'Model inputs'!B186*'Model inputs'!B182 -> 249.59191 | M67: ='Model inputs'!M79*'Model inputs'!B186*'Model inputs'!B182 -> 322.57042 | N67: ='Model inputs'!N79*'Model inputs'!B186*'Model inputs'!B182 -> 413.47615 | O67: ='Model inputs'!O79*'Model inputs'!B186*'Model inputs'!B182 -> 526.80041 | P67: ='Model inputs'!P79*'Model inputs'!B186*'Model inputs'!B182 -> 668.15708
A68: Overage revenue | P68: =SUM('Model inputs'!P69,'Model inputs'!P70,'Model inputs'!P71) -> 2935.4721
A69: Overage revenue > Maintainer | P69: ='Model inputs'!P81*'Model inputs'!B276*'Model inputs'!B268 -> 226.20578
A70: Overage revenue > Starter | P70: ='Model inputs'!P82*'Model inputs'!B277*'Model inputs'!B269 -> 909.41018
A71: Overage revenue > Team | P71: ='Model inputs'!P83*'Model inputs'!B278*'Model inputs'!B270 -> 1799.8561
A72: Overage revenue | P72: =SUM('Model inputs'!P73,'Model inputs'!P74,'Model inputs'!P75) -> 256.93189
A73: Overage revenue > Maintainer | P73: ='Model inputs'!P85*'Model inputs'!B280*'Model inputs'!B272 -> 17.828399
A74: Overage revenue > Starter | P74: ='Model inputs'!P86*'Model inputs'!B281*'Model inputs'!B273 -> 76.7697
A75: Overage revenue > Team | P75: ='Model inputs'!P87*'Model inputs'!B282*'Model inputs'!B274 -> 162.33379
A76: Paying customers | D76: =SUM('Model inputs'!D77,'Model inputs'!D78,'Model inputs'!D79) -> 0 | E76: =SUM('Model inputs'!E77,'Model inputs'!E78,'Model inputs'!E79) -> 3 | F76: =SUM('Model inputs'!F77,'Model inputs'!F78,'Model inputs'!F79) -> 6.564 | G76: =SUM('Model inputs'!G77,'Model inputs'!G78,'Model inputs'!G79) -> 10.84563 | H76: =SUM('Model inputs'!H77,'Model inputs'!H78,'Model inputs'!H79) -> 16.036016 | I76: =SUM('Model inputs'!I77,'Model inputs'!I78,'Model inputs'!I79) -> 22.373223 | J76: =SUM('Model inputs'!J77,'Model inputs'!J78,'Model inputs'!J79) -> 30.154051 | K76: =SUM('Model inputs'!K77,'Model inputs'!K78,'Model inputs'!K79) -> 39.74878 | ... P76: =SUM('Model inputs'!P77,'Model inputs'!P78,'Model inputs'!P79) -> 135.7862
A77: Paying customers > Maintainer | D77: =0 -> 0 | E77: ='Model inputs'!D77*(1-'Torque Assumptions · Tier prici'!H5)+'Model inputs'!E58*'Model inputs'!B143 -> 1.5 | F77: ='Model inputs'!E77*(1-'Torque Assumptions · Tier prici'!H5)+'Model inputs'!F58*'Model inputs'!B143 -> 3.255 | G77: ='Model inputs'!F77*(1-'Torque Assumptions · Tier prici'!H5)+'Model inputs'!G58*'Model inputs'!B143 -> 5.33835 | H77: ='Model inputs'!G77*(1-'Torque Assumptions · Tier prici'!H5)+'Model inputs'!H58*'Model inputs'!B143 -> 7.8409695 | I77: ='Model inputs'!H77*(1-'Torque Assumptions · Tier prici'!H5)+'Model inputs'!I58*'Model inputs'!B143 -> 10.875801 | J77: ='Model inputs'!I77*(1-'Torque Assumptions · Tier prici'!H5)+'Model inputs'!J58*'Model inputs'!B143 -> 14.583374 | K77: ='Model inputs'!J77*(1-'Torque Assumptions · Tier prici'!H5)+'Model inputs'!K58*'Model inputs'!B143 -> 19.13875 | L77: ='Model inputs'!K77*(1-'Torque Assumptions · Tier prici'!H5)+'Model inputs'!L58*'Model inputs'!B143 -> 24.760207 | M77: ='Model inputs'!L77*(1-'Torque Assumptions · Tier prici'!H5)+'Model inputs'!M58*'Model inputs'!B143 -> 31.720087 | N77: ='Model inputs'!M77*(1-'Torque Assumptions · Tier prici'!H5)+'Model inputs'!N58*'Model inputs'!B143 -> 40.358351 | O77: ='Model inputs'!N77*(1-'Torque Assumptions · Tier prici'!H5)+'Model inputs'!O58*'Model inputs'!B143 -> 51.099522 | P77: ='Model inputs'!O77*(1-'Torque Assumptions · Tier prici'!H5)+'Model inputs'!P58*'Model inputs'!B143 -> 64.473858
A78: Paying customers > Starter | D78: =0 -> 0 | E78: ='Model inputs'!D78*(1-'Torque Assumptions · Tier prici'!H6)+'Model inputs'!E58*'Model inputs'!B144 -> 1.05 | F78: ='Model inputs'!E78*(1-'Torque Assumptions · Tier prici'!H6)+'Model inputs'!F58*'Model inputs'!B144 -> 2.31 | G78: ='Model inputs'!F78*(1-'Torque Assumptions · Tier prici'!H6)+'Model inputs'!G58*'Model inputs'!B144 -> 3.835125 | H78: ='Model inputs'!G78*(1-'Torque Assumptions · Tier prici'!H6)+'Model inputs'!H58*'Model inputs'!B144 -> 5.69415 | I78: ='Model inputs'!H78*(1-'Torque Assumptions · Tier prici'!H6)+'Model inputs'!I58*'Model inputs'!B144 -> 7.9729191 | J78: ='Model inputs'!I78*(1-'Torque Assumptions · Tier prici'!H6)+'Model inputs'!J58*'Model inputs'!B144 -> 10.778619 | K78: ='Model inputs'!J78*(1-'Torque Assumptions · Tier prici'!H6)+'Model inputs'!K58*'Model inputs'!B144 -> 14.24512 | L78: ='Model inputs'!K78*(1-'Torque Assumptions · Tier prici'!H6)+'Model inputs'!L58*'Model inputs'!B144 -> 18.539654 | M78: ='Model inputs'!L78*(1-'Torque Assumptions · Tier prici'!H6)+'Model inputs'!M58*'Model inputs'!B144 -> 23.871159 | N78: ='Model inputs'!M78*(1-'Torque Assumptions · Tier prici'!H6)+'Model inputs'!N58*'Model inputs'!B144 -> 30.500711 | O78: ='Model inputs'!N78*(1-'Torque Assumptions · Tier prici'!H6)+'Model inputs'!O58*'Model inputs'!B144 -> 38.754562 | P78: ='Model inputs'!O78*(1-'Torque Assumptions · Tier prici'!H6)+'Model inputs'!P58*'Model inputs'!B144 -> 49.040443
A79: Paying customers > Team | D79: =0 -> 0 | E79: ='Model inputs'!D79*(1-'Torque Assumptions · Tier prici'!H7)+'Model inputs'!E58*'Model inputs'!B145 -> 0.45 | F79: ='Model inputs'!E79*(1-'Torque Assumptions · Tier prici'!H7)+'Model inputs'!F58*'Model inputs'!B145 -> 0.999 | G79: ='Model inputs'!F79*(1-'Torque Assumptions · Tier prici'!H7)+'Model inputs'!G58*'Model inputs'!B145 -> 1.672155 | H79: ='Model inputs'!G79*(1-'Torque Assumptions · Tier prici'!H7)+'Model inputs'!H58*'Model inputs'!B145 -> 2.5008966 | I79: ='Model inputs'!H79*(1-'Torque Assumptions · Tier prici'!H7)+'Model inputs'!I58*'Model inputs'!B145 -> 3.5245025 | J79: ='Model inputs'!I79*(1-'Torque Assumptions · Tier prici'!H7)+'Model inputs'!J58*'Model inputs'!B145 -> 4.7920585 | K79: ='Model inputs'!J79*(1-'Torque Assumptions · Tier prici'!H7)+'Model inputs'!K58*'Model inputs'!B145 -> 6.3649105 | L79: ='Model inputs'!K79*(1-'Torque Assumptions · Tier prici'!H7)+'Model inputs'!L58*'Model inputs'!B145 -> 8.3197304 | M79: ='Model inputs'!L79*(1-'Torque Assumptions · Tier prici'!H7)+'Model inputs'!M58*'Model inputs'!B145 -> 10.752347 | N79: ='Model inputs'!M79*(1-'Torque Assumptions · Tier prici'!H7)+'Model inputs'!N58*'Model inputs'!B145 -> 13.782538 | O79: ='Model inputs'!N79*(1-'Torque Assumptions · Tier prici'!H7)+'Model inputs'!O58*'Model inputs'!B145 -> 17.560014 | P79: ='Model inputs'!O79*(1-'Torque Assumptions · Tier prici'!H7)+'Model inputs'!P58*'Model inputs'!B145 -> 22.271903
A80: Paying customers | P80: =SUM('Model inputs'!P81,'Model inputs'!P82,'Model inputs'!P83) -> 375.68726
A81: Paying customers > Maintainer | P81: ='Model inputs'!O284*(1-'Model inputs'!B238)+'Model inputs'!P265*'Model inputs'!B258 -> 180.96462
A82: Paying customers > Starter | P82: ='Model inputs'!O285*(1-'Model inputs'!B239)+'Model inputs'!P265*'Model inputs'!B259 -> 134.72743
A83: Paying customers > Team | P83: ='Model inputs'!O286*(1-'Model inputs'!B240)+'Model inputs'!P265*'Model inputs'!B260 -> 59.995204
A84: Paying customers | P84: =SUM('Model inputs'!P85,'Model inputs'!P86,'Model inputs'!P87) -> 31.047134
A85: Paying customers > Maintainer | P85: ='Model inputs'!O288*(1-'Model inputs'!B242)+'Model inputs'!P266*'Model inputs'!B262 -> 14.262719
A86: Paying customers > Starter | P86: ='Model inputs'!O289*(1-'Model inputs'!B243)+'Model inputs'!P266*'Model inputs'!B263 -> 11.373289
A87: Paying customers > Team | P87: ='Model inputs'!O290*(1-'Model inputs'!B244)+'Model inputs'!P266*'Model inputs'!B264 -> 5.4111263
A88: Payment processing cost · Torque Plan Summary · Scenario comparison: month 12 (Sep 2027) · Main Scenario | D88: 0 | E88: ='Model inputs'!E121*'Model inputs'!B148+SUM('Model inputs'!E77,'Model inputs'!E78,'Model inputs'!E79)*'Model inputs'!B146 -> 11.034413 | F88: ='Model inputs'!F121*'Model inputs'!B148+SUM('Model inputs'!F77,'Model inputs'!F78,'Model inputs'!F79)*'Model inputs'!B146 -> 24.3374 | G88: ='Model inputs'!G121*'Model inputs'!B148+SUM('Model inputs'!G77,'Model inputs'!G78,'Model inputs'!G79)*'Model inputs'!B146 -> 40.501406 | H88: ='Model inputs'!H121*'Model inputs'!B148+SUM('Model inputs'!H77,'Model inputs'!H78,'Model inputs'!H79)*'Model inputs'!B146 -> 60.265484 | I88: ='Model inputs'!I121*'Model inputs'!B148+SUM('Model inputs'!I77,'Model inputs'!I78,'Model inputs'!I79)*'Model inputs'!B146 -> 84.552049 | J88: ='Model inputs'!J121*'Model inputs'!B148+SUM('Model inputs'!J77,'Model inputs'!J78,'Model inputs'!J79)*'Model inputs'!B146 -> 114.51281 | K88: ='Model inputs'!K121*'Model inputs'!B148+SUM('Model inputs'!K77,'Model inputs'!K78,'Model inputs'!K79)*'Model inputs'!B146 -> 151.58618 | L88: ='Model inputs'!L121*'Model inputs'!B148+SUM('Model inputs'!L77,'Model inputs'!L78,'Model inputs'!L79)*'Model inputs'!B146 -> 197.56902 | M88: ='Model inputs'!M121*'Model inputs'!B148+SUM('Model inputs'!M77,'Model inputs'!M78,'Model inputs'!M79)*'Model inputs'!B146 -> 254.70636 | N88: ='Model inputs'!N121*'Model inputs'!B148+SUM('Model inputs'!N77,'Model inputs'!N78,'Model inputs'!N79)*'Model inputs'!B146 -> 325.80346 | O88: ='Model inputs'!O121*'Model inputs'!B148+SUM('Model inputs'!O77,'Model inputs'!O78,'Model inputs'!O79)*'Model inputs'!B146 -> 414.36597 | P88: ='Model inputs'!P121*'Model inputs'!B148+SUM('Model inputs'!P77,'Model inputs'!P78,'Model inputs'!P79)*'Model inputs'!B146 -> 524.77508
A89: Payment processing cost · Optimistic | P89: ='Torque Plan Summary · Scenario'!D7*'Model inputs'!B297+SUM('Model inputs'!P81,'Model inputs'!P82,'Model inputs'!P83)*'Model inputs'!B295 -> 1431.0331
A90: Payment processing cost · Conservative | P90: ='Torque Plan Summary · Scenario'!C7*'Model inputs'!B298+SUM('Model inputs'!P85,'Model inputs'!P86,'Model inputs'!P87)*'Model inputs'!B296 -> 124.02497
A91: Sandbox compute cost · Torque Plan Summary · Scenario comparison: month 12 (Sep 2027) · Main Scenario | D91: 0 | E91: =SUM('Model inputs'!E26,'Model inputs'!E27,'Model inputs'!E28)*'Model inputs'!B154 -> 10.76985 | F91: =SUM('Model inputs'!F26,'Model inputs'!F27,'Model inputs'!F28)*'Model inputs'!B154 -> 23.77791 | G91: =SUM('Model inputs'!G26,'Model inputs'!G27,'Model inputs'!G28)*'Model inputs'!B154 -> 39.605936 | H91: =SUM('Model inputs'!H26,'Model inputs'!H27,'Model inputs'!H28)*'Model inputs'!B154 -> 58.979867 | I91: =SUM('Model inputs'!I26,'Model inputs'!I27,'Model inputs'!I28)*'Model inputs'!B154 -> 82.805951 | J91: =SUM('Model inputs'!J26,'Model inputs'!J27,'Model inputs'!J28)*'Model inputs'!B154 -> 112.21589 | K91: =SUM('Model inputs'!K26,'Model inputs'!K27,'Model inputs'!K28)*'Model inputs'!B154 -> 148.6233 | L91: =SUM('Model inputs'!L26,'Model inputs'!L27,'Model inputs'!L28)*'Model inputs'!B154 -> 193.7942 | M91: =SUM('Model inputs'!M26,'Model inputs'!M27,'Model inputs'!M28)*'Model inputs'!B154 -> 249.93524 | N91: =SUM('Model inputs'!N26,'Model inputs'!N27,'Model inputs'!N28)*'Model inputs'!B154 -> 319.80385 | O91: =SUM('Model inputs'!O26,'Model inputs'!O27,'Model inputs'!O28)*'Model inputs'!B154 -> 406.84604 | P91: =SUM('Model inputs'!P26,'Model inputs'!P27,'Model inputs'!P28)*'Model inputs'!B154 -> 515.36857
A92: Sandbox compute cost · Optimistic | P92: =SUM('Model inputs'!P30,'Model inputs'!P31,'Model inputs'!P32)*'Model inputs'!B299 -> 1102.6395
A93: Sandbox compute cost · Conservative | P93: =SUM('Model inputs'!P34,'Model inputs'!P35,'Model inputs'!P36)*'Model inputs'!B300 -> 167.94325
A94: Software and tools · Torque Plan Summary · Scenario comparison: month 12 (Sep 2027) · Main Scenario | D94: 0 | E94: =IF('Model inputs'!B156="","",'Model inputs'!B156) -> 200 | F94: =IF('Model inputs'!B156="","",'Model inputs'!B156) -> 200 | G94: =IF('Model inputs'!B156="","",'Model inputs'!B156) -> 200 | H94: =IF('Model inputs'!B156="","",'Model inputs'!B156) -> 200 | I94: =IF('Model inputs'!B156="","",'Model inputs'!B156) -> 200 | J94: =IF('Model inputs'!B156="","",'Model inputs'!B156) -> 200 | K94: =IF('Model inputs'!B156="","",'Model inputs'!B156) -> 200 | L94: =IF('Model inputs'!B156="","",'Model inputs'!B156) -> 200 | M94: =IF('Model inputs'!B156="","",'Model inputs'!B156) -> 200 | N94: =IF('Model inputs'!B156="","",'Model inputs'!B156) -> 200 | O94: =IF('Model inputs'!B156="","",'Model inputs'!B156) -> 200 | P94: =IF('Model inputs'!B156="","",'Model inputs'!B156) -> 200
A95: Software and tools · Optimistic | P95: =IF('Model inputs'!B301="","",'Model inputs'!B301) -> 200
A96: Software and tools · Conservative | P96: =IF('Model inputs'!B302="","",'Model inputs'!B302) -> 200
A97: Storage cost · Torque Plan Summary · Scenario comparison: month 12 (Sep 2027) · Main Scenario | D97: 0 | E97: =SUM('Model inputs'!E26,'Model inputs'!E27,'Model inputs'!E28)*'Model inputs'!B158 -> 0.690375 | F97: =SUM('Model inputs'!F26,'Model inputs'!F27,'Model inputs'!F28)*'Model inputs'!B158 -> 1.524225 | G97: =SUM('Model inputs'!G26,'Model inputs'!G27,'Model inputs'!G28)*'Model inputs'!B158 -> 2.5388421 | H97: =SUM('Model inputs'!H26,'Model inputs'!H27,'Model inputs'!H28)*'Model inputs'!B158 -> 3.7807607 | I97: =SUM('Model inputs'!I26,'Model inputs'!I27,'Model inputs'!I28)*'Model inputs'!B158 -> 5.3080738 | J97: =SUM('Model inputs'!J26,'Model inputs'!J27,'Model inputs'!J28)*'Model inputs'!B158 -> 7.1933265 | K97: =SUM('Model inputs'!K26,'Model inputs'!K27,'Model inputs'!K28)*'Model inputs'!B158 -> 9.5271346 | L97: =SUM('Model inputs'!L26,'Model inputs'!L27,'Model inputs'!L28)*'Model inputs'!B158 -> 12.422705 | M97: =SUM('Model inputs'!M26,'Model inputs'!M27,'Model inputs'!M28)*'Model inputs'!B158 -> 16.021489 | N97: =SUM('Model inputs'!N26,'Model inputs'!N27,'Model inputs'!N28)*'Model inputs'!B158 -> 20.500247 | O97: =SUM('Model inputs'!O26,'Model inputs'!O27,'Model inputs'!O28)*'Model inputs'!B158 -> 26.079874 | P97: =SUM('Model inputs'!P26,'Model inputs'!P27,'Model inputs'!P28)*'Model inputs'!B158 -> 33.036447
A98: Storage cost · Optimistic | P98: =SUM('Model inputs'!P30,'Model inputs'!P31,'Model inputs'!P32)*'Model inputs'!B303 -> 76.572189
A99: Storage cost · Conservative | P99: =SUM('Model inputs'!P34,'Model inputs'!P35,'Model inputs'!P36)*'Model inputs'!B304 -> 9.6519108
A100: Subscription revenue | D100: =SUM('Model inputs'!D101,'Model inputs'!D102,'Model inputs'!D103) -> 0 | E100: =SUM('Model inputs'!E101,'Model inputs'!E102,'Model inputs'!E103) -> 327 | F100: =SUM('Model inputs'!F101,'Model inputs'!F102,'Model inputs'!F103) -> 721.686 | G100: =SUM('Model inputs'!G101,'Model inputs'!G102,'Model inputs'!G103) -> 1201.6794 | H100: =SUM('Model inputs'!H101,'Model inputs'!H102,'Model inputs'!H103) -> 1788.9667 | I100: =SUM('Model inputs'!I101,'Model inputs'!I102,'Model inputs'!I103) -> 2510.9937 | J100: =SUM('Model inputs'!J101,'Model inputs'!J102,'Model inputs'!J103) -> 3402.0324 | K100: =SUM('Model inputs'!K101,'Model inputs'!K102,'Model inputs'!K103) -> 4504.8899 | ... P100: =SUM('Model inputs'!P101,'Model inputs'!P102,'Model inputs'!P103) -> 15611.235
A101: Subscription revenue > Maintainer | D101: =0 -> 0 | E101: ='Model inputs'!E77*'Model inputs'!B176 -> 43.5 | F101: ='Model inputs'!F77*'Model inputs'!B176 -> 94.395 | G101: ='Model inputs'!G77*'Model inputs'!B176 -> 154.81215 | H101: ='Model inputs'!H77*'Model inputs'!B176 -> 227.38812 | I101: ='Model inputs'!I77*'Model inputs'!B176 -> 315.39824 | J101: ='Model inputs'!J77*'Model inputs'!B176 -> 422.91784 | K101: ='Model inputs'!K77*'Model inputs'!B176 -> 555.02375 | L101: ='Model inputs'!L77*'Model inputs'!B176 -> 718.04601 | M101: ='Model inputs'!M77*'Model inputs'!B176 -> 919.88254 | N101: ='Model inputs'!N77*'Model inputs'!B176 -> 1170.3922 | O101: ='Model inputs'!O77*'Model inputs'!B176 -> 1481.8861 | P101: ='Model inputs'!P77*'Model inputs'!B176 -> 1869.7419
...
